Workbook
Name total_reducido: 'Study selection'!$A$1:$BB$135

Sheet Study selection
B1: authors | C1: author full names | D1: author(s) id | E1: title | F1: year | G1: source title | H1: volume | I1: issue | J1: art. no. | K1: page start | L1: page end | M1: page count | N1: cited by | O1: doi | P1: link | Q1: affiliations | R1: authors with affiliations | S1: abstract | T1: author keywords | U1: index keywords | V1: molecular sequence numbers | W1: chemicals/cas | X1: tradenames | Y1: manufacturers | Z1: funding details | AA1: funding texts | AB1: references | AC1: correspondence address | AD1: editors | AE1: publisher | AF1: sponsors | AG1: conference name | AH1: conference date | AI1: conference location | AJ1: conference code | AK1: issn | AL1: isbn | AM1: coden | AN1: pubmed id | AO1: language of original document | AP1: abbreviated source title | AQ1: document type | AR1: publication stage | AS1: open access | AT1: source | AU1: eid | AV1: query | AW1: search_engine | AX1: peer_review_conference | AY1: peer_review_color | AZ1: peer_review_publisher | BA1: peer_review_color | BB1: peer_review_abbreviation | BC1: peer_review_color | BD1: title | BE1: abstract | BF1: full text | BG1: choosen | BH1: choosen_state | BI1: downloaded | BJ1: done | BK1: notes
A2: 154 | B2: Chen J.; Verspoor K.; Zhai Z. | C2: Chen, Jiyu (57216991109); Verspoor, Karin (12772581800); Zhai, Zenan (57216645849) | D2: 57216991109; 12772581800; 57216645849 | E2: A bag-of-concepts model improves relation extraction in a narrow knowledge domain with limited data | F2: 2019.0 | G2: NAACL HLT 2019 - 2019 Conference of the North American Chapter of the Association for Computational Linguistics: Human Language Technologies - Proceedings of the Student Research Workshop | K2: 43.0 | L2: 52.0 | M2: 9.0 | N2: 2.0 | P2: https://www.scopus.com/inward/record.uri?eid=2-s2.0-85085638027&partnerID=40&md5=b29a1a9e22b0c9dc26388717597a8950 | Q2: School of Computing and Information Systems, University of Melbourne, Australia | R2: Chen J., School of Computing and Information Systems, University of Melbourne, Australia; Verspoor K., School of Computing and Information Systems, University of Melbourne, Australia; Zhai Z., School of Computing and Information Systems, University of Melbourne, Australia | S2: This paper focuses on a traditional relation extraction task in the context of limited annotated data and a narrow knowledge domain. We explore this task with a clinical corpus consisting of 200 breast cancer follow-up treatment letters in which 16 distinct types of relations are annotated. We experiment with an approach to extracting typed relations called windowbounded co-occurrence (WBC), which uses an adjustable context window around entity mentions of a relevant type, and compare its performance with a more typical intra-sentential co-occurrence baseline. We further introduce a new bag-of-concepts (BoC) approach to feature engineering based on the state-of-the-art word embeddings and word synonyms. We demonstrate the competitiveness of BoC by comparing with methods of higher complexity, and explore its effectiveness on this small dataset. ¬© 2017 Association for Computational Linguistics. | U2: Computational linguistics; Extraction; Breast Cancer; Co-occurrence; Context window; Feature engineerings; Knowledge domains; Relation extraction; State of the art; Types of relations; Data mining | AB2: Ben Abacha A., Zweigenbaum P., Automatic extraction of semantic relations between medical entities: A rule based approach, Journal of Biomedical Semantics, 2, 5, (2011); Ammar W., Peters M., Bhagavatula C., Power R., The AI2 system at SemEval-2017 Task 10 (ScienceIE): Semisupervised end-to-end entity and relation extraction, Proceedings of the 11th International Workshop on Semantic Evaluation (SemEval-2017), pp. 592-596, (2017); Aronson A.R., Effective mapping of biomedical text to the UMLS Metathesaurus: The MetaMap program, Proceedings of the AMIA Symposium, (2001); Bird S., Klein E., Loper E., Natural Language Processing with Python: Analyzing Text with the Natural Language Toolkit, (2009); Brown P.F., Desouza P.V., Mercer R.L., Pietra Della V.J., Lai J.C., Class-based n-gram models of natural language, Computational Linguistics, 18, 4, pp. 467-479, (1992); Chaix E., Dubreucq B., Fatihi A., Valsamou D., Bossy R., Ba M., Deleger L., Zweigenbaum P., Bessieres P., Lepiniec L., Et al., Overview of the Regulatory Network of Plant Seed Development (SeeDev) Task at the BioNLP Shared Task 2016, Proceedings of the 4th BioNLP Shared Task Workshop, pp. 1-11, (2016); Chollet F., Et al., Keras, (2015); Fundel K., Kuffner R., Zimmer R., RelExRelation extraction using dependency parse trees, Bioinformatics, 23, 3, pp. 365-371, (2006); Funk C., Baumgartner W., Garcia B., Roeder C., Bada M., Cohen K., Hunter L., Verspoor K., Largescale biomedical concept recognition: An evaluation of current automatic annotators and their parameters, BMC Bioinformatics, 15, 1, (2014); Hagberg A., Swart P., Chult D.S., Exploring Network Structure, Dynamics, and Function Using NetworkX, (2008); Hearst M.A., Support Vector Machines, IEEE Intelligent Systems, 13, 4, pp. 18-28, (1998); Yao Huang Y., Yang Wang W., Deep Residual Learning for Weakly-Supervised Relation Extraction, Proceedings of the 2017 Conference on Empirical Methods in Natural Language Processing, EMNLP 2017, pp. 1803-1807, (2017); Li J., Sun Y., Johnson R.J., Sciaky D., Wei C., Leaman R., Peter Davis A., Mattingly C.J., Wiegers T., Lu Z., Biocreative v Cdr Task Corpus: A Resource for Chemical Disease Relation Extraction, (2016); Liu H., Hunter L., Keselj V., Verspoor K., Approximate subgraph matchingbased literature mining for biomedical events and relations, PloS One, 8, 4, (2013); Manning C., Surdeanu M., Bauer J., Finkel J., Bethard S., McClosky D., The Stanford CoreNLP natural language processing toolkit, Proceedings of 52nd Annual Meeting of the Association for Computational Linguistics: System Demonstrations, pp. 55-60, (2014); Mikolov T., Chen K., Corrado G., Dean J., Efficient estimation of word representations in vector space, CoRR, (2013); Mikolov T., Sutskever I., Chen K., Corrado G.S., Dean J., Distributed representations of words and phrases and their compositionality, Advances in Neural Information Processing Systems, pp. 3111-3119, (2013); Moen S., Salakoski T., Sophia A., Distributional semantics resources for biomedical text processing, Proceedings of the 5th International Symposium on Languages in Biology and Medicine, pp. 39-43, (2013); Quoc Nguyen D., Verspoor K., Convolutional neural networks for chemical-disease relation extraction are improved with character-based word embeddings, Proceedings of the BioNLP 2018 Workshop, pp. 129-136, (2018); Huu Nguyen T., Grishman R., Combining Neural Networks and Log-linear Models to Improve Relation Extraction, Proceedings of IJCAI Workshop on Deep Learning for Artificial Intelligence (DLAI), (2016); Panyam N.C., Verspoor K., Cohn T., Kotagiri R., ASM Kernel: Graph Kernel using Approximate Subgraph Matching for Relation Extraction, Proceedings of the Australasian Language Technology Association Workshop 2016, pp. 65-73, (2016); Pedregosa F., Varoquaux G., Gramfort A., Michel V., Thirion B., Grisel O., Blondel M., Prettenhofer P., Weiss R., Dubourg V., Vanderplas J., Passos A., Cournapeau D., Brucher M., Perrot M., Duchesnay E., Scikit-learn: Machine learning in Python, Journal of Machine Learning Research, 12, pp. 2825-2830, (2011); Peng N., Poon H., Quirk C., Toutanova K., Yih W., Cross-Sentence N-ary Relation Extraction with Graph LSTMs, Transactions of the Association of Computational Linguistics, 5, 1, pp. 101-115, (2017); Pennington J., Socher R., Manning C., Glove: Global vectors for word representation, Proceedings of the 2014 Conference on Empirical Methods in Natural Language Processing (EMNLP), pp. 1532-1543, (2014); Pitson G., Banks P., Cavedon L., Verspoor K., Developing a Manually Annotated Corpus of Clinical Letters for Breast Cancer Patients on Routine Follow-Up, Studies in Health Technology and Informatics, 235, pp. 196-200, (2017); Rehurek R., Sojka P., Software framework for topic modelling with large corpora, Proceedings of the LREC 2010 Workshop on New Challenges for NLP Frameworks, (2010); Sahlgren M., Coster R., Using bag-of-concepts to improve the performance of support vector machines in text categorization, Proceedings of the 20th International Conference on Computational Linguistics, (2004); Song M., Chul Kim W., Lee D., Eun Heo G., Young Kang K., PKDE4J: Entity and relation extraction for public knowledge discovery, Journal of Biomedical Informatics, 57, pp. 320-332, (2015); Turian J., Ratinov L., Bengio Y., Word representations: A simple and general method for semi-supervised learning, Proceedings of the 48th Annual Meeting of the Association for Computational Linguistics, pp. 384-394, (2010); Verspoor K., Jimeno Yepes A., Cavedon L., McIntosh T., Herten-Crabb A., Thomas Z., Plazzer J., Annotating the biomedical literature for the human variome, Database 2013, (2013); Verspoor K.M., Eun Heo G., Young Kang K., Song M., Establishing a baseline for literature mining human genetic variants and their relationships to disease cohorts, BMC Medical Informatics and Decision Making, 16, 1, (2016); Wei C., Peng Y., Leaman R., Peter Davis A., Mattingly C.J., Li J., Wiegers T.C., Lu Z., Overview of the BioCreative V chemical disease relation (CDR) task, Proceedings of the Fifth BioCreative Challenge Evaluation Workshop, pp. 154-166, (2015) | AC2: J. Chen; School of Computing and Information Systems, University of Melbourne, Australia; email: jiyuc@student.unimelb.edu.au | AE2: Association for Computational Linguistics (ACL) | AG2: 2019 Conference of the North American Chapter of the Association for Computational Linguistics: Human Language Technologies, NAACL HLT 2019 - Student Research Workshop, SRW 2019 | AH2: 3 June 2019 through 5 June 2019 | AI2: Minneapolis | AJ2: 159853.0 | AL2: 978-195073715-4 | AO2: English | AP2: NAACL HLT - Conf. N. Am. Chapter Assoc. Comput. Linguistics: Hum. Lang. Technol. - Proc. Stud. Res. Workshop | AQ2: Conference paper | AR2: Final | AT2: Scopus | AU2: 2-s2.0-85085638027 | AV2: q3 | AW2: Scopus | AX2: TRUE | AY2: =IF(AX2=TRUE,1,IF(AX2=FALSE,0,-1)) -> 1 | AZ2: TRUE | BA2: =IF(AZ2=TRUE,1,IF(AZ2=FALSE,0,-1)) -> 1 | BB2: TRUE | BC2: =IF(BB2=TRUE,1,IF(BB2=FALSE,0,-1)) -> 1 | BD2: 1 | BE2: 1 | BF2: 0 | BG2: 0 | BH2: =IF(BG2=1,"Yes",IF(BG2=-1,"Doubt","No")) -> No | BI2: =IF(BF2=1,"Yes","No") -> No | BJ2: 0 | BK2: It is focused on biomedical domain. It talks about improve relation classsification by a Bag-of-concepts and context.
A3: 52 | B3: Zhao X.; Deng Y.; Yang M.; Wang L.; Zhang R.; Cheng H.; Lam W.; Shen Y.; Xu R. | C3: Zhao, Xiaoyan (57218707688); Deng, Yang (57200607347); Yang, Min (56349712700); Wang, Lingzhi (57216694549); Zhang, Rui (54947068500); Cheng, Hong (7404284983); Lam, Wai (57203073460); Shen, Ying (56763084800); Xu, Ruifeng (56048299800) | D3: 57218707688; 57200607347; 56349712700; 57216694549; 54947068500; 7404284983; 57203073460; 56763084800; 56048299800 | E3: A Comprehensive Survey on Relation Extraction: Recent Advances and New Frontiers | F3: 2024.0 | G3: ACM Computing Surveys | H3: 56 | I3: 11.0 | J3: 293 | N3: 7.0 | O3: 10.1145/3674501 | P3: https://www.scopus.com/inward/record.uri?eid=2-s2.0-85200560529&doi=10.1145%2f3674501&partnerID=40&md5=7f8fd6f9a70dcf2e17d9ffb2ebc9559e | Q3: The Chinese University of Hong Kong, Hong Kong, Hong Kong; Singapore Management University, Singapore, Singapore; Shenzhen Institutes of Advanced Technology, Chinese Academy of Sciences, Guangdong, Shenzhen, China; Huazhong University of Science and Technology, Wuhan, China; Sun Yat-Sen University, Guangdong, Shenzhen, China; Harbin Institute of Technology Shenzhen, GuanDong, Shenzhen, China | R3: Zhao X., The Chinese University of Hong Kong, Hong Kong, Hong Kong; Deng Y., Singapore Management University, Singapore, Singapore; Yang M., Shenzhen Institutes of Advanced Technology, Chinese Academy of Sciences, Guangdong, Shenzhen, China; Wang L., The Chinese University of Hong Kong, Hong Kong, Hong Kong; Zhang R., Huazhong University of Science and Technology, Wuhan, China; Cheng H., The Chinese University of Hong Kong, Hong Kong, Hong Kong; Lam W., The Chinese University of Hong Kong, Hong Kong, Hong Kong; Shen Y., Sun Yat-Sen University, Guangdong, Shenzhen, China; Xu R., Harbin Institute of Technology Shenzhen, GuanDong, Shenzhen, China | S3: Relation extraction (RE) involves identifying the relations between entities from underlying content. RE serves as the foundation for many natural language processing (NLP) and information retrieval applications, such as knowledge graph completion and question answering. In recent years, deep neural networks have dominated the field of RE and made noticeable progress. Subsequently, the large pre-trained language models (PLMs) have taken the state-of-the-art RE to a new level. This survey provides a comprehensive review of existing deep learning techniques for RE. First, we introduce RE resources, including datasets and evaluation metrics. Second, we propose a new taxonomy to categorize existing works from three perspectives, i.e., text representation, context encoding, and triplet prediction. Third, we discuss several important challenges faced by RE and summarize potential techniques to tackle these challenges. Finally, we outline some promising future directions and prospects in this field. This survey is expected to facilitate researchers‚Äô collaborative efforts to address the challenges of real-world RE systems. ¬© 2024 Copyright held by the owner/author(s). Publication rights licensed to ACM. | T3: deep learning; low-resource relation extraction; pre-trained language models; Relation extraction | U3: Computational linguistics; Extraction; Knowledge graph; Learning systems; Natural language processing systems; Deep learning; Language informations; Language model; Language processing; Low-resource relation extraction; Natural languages; Pre-trained language model; Relation extraction; Retrieval applications; Deep neural networks | Z3: Research Grants Council, University Grants Committee, Á†îÁ©∂Ë≥áÂä©Â±Ä, (CUHK 14217622); Shenzhen Basic Research Foundation, (JCYJ20210324115614039); Shenzhen Science and Technology Innovation Program, (KQTD20190929172835662); National Natural Science Foundation of China, NSFC, (62376262); Natural Science Foundation of Guangdong Province, (2024A1515030166); National Key Research and Development Program of China, NKRDPC, (2022YFF0902100) | AA3: This research is supported in part by grants from the Research Grant Council of the Hong Kong Special Administrative Region, China (No. CUHK 14217622). Min Yang was supported by National Key Research and Development Program of China (2022YFF0902100), National Natural Science Foundation of China (62376262), the Natural Science Foundation of Guangdong Province of China (2024A1515030166), Shenzhen Science and Technology Innovation Program (KQTD20190929172835662), Shenzhen Basic Research Foundation (JCYJ20210324115614039). | AB3: Achiam J., Adler S., Agarwal S., Ahmad L., Akkaya I., Aleman F.L., Almeida D., Altenschmidt J., Altman S., Anadkat S., Gpt-4 technical report, (2023); Agrawal M., Hegselmann S., Lang H., Kim Y., Sontag D., Large language models are few-shot clinical information extractors, Proceedings of the 2022 Conference on Empirical Methods in Natural Language Processing, pp. 1998-2022, (2022); Ahmed M., Islam J., Samee M.R., Mercer R.E., Identifying protein-protein interaction using tree LSTM and structured attention, Proceedings of the 2019 IEEE 13th International Conference on Semantic Computing (ICSC), pp. 224-231, (2019); Albalak A., Embar V., Tuan Y.-L., Getoor L., Wang W.Y., D-REX: Dialogue relation extraction with explanations, Proceedings of the 4th Workshop on NLP for Conversational AI, pp. 34-46, (2022); Andrew J.J., Automatic extraction of entities and relation from legal documents, Proceedings of the 7th Named Entities Workshop, pp. 1-8, (2018); Andrew J.J., Automatic extraction of entities and relation from legal documents, Proceedings of the NEWS@ACL, (2018); Asada M., Integrating heterogeneous domain information into relation extraction: A case study on drug-drug interaction extraction, (2022); Augenstein I., Das M., Riedel S., Vikraman L., McCallum A., SemEval 2017 Task 10: ScienceIE - extracting keyphrases and relations from scientific publications, Proceedings of the International Workshop on Semantic Evaluation, (2017); Pawar S., Palshikar G.K., Bhattacharyya P., Relation extraction: A survey, (2017); Bassignana E., Plank B., What do you mean by relation extraction? a survey on datasets and study on scientific relation classification, Proceedings of the Annual Meeting of the Association for Computational Linguistics, (2022); Beltagy I., Lo K., Cohan A., SciBERT: A pretrained language model for scientific text, Proceedings of the 2019 Conference on Empirical Methods in Natural Language Processing and the 9th International Joint Conference on Natural Language Processing (EMNLP-IJCNLP), pp. 3615-3620, (2019); Bhartiya A., Badola K., Mausam, DiS-ReX: A multilingual dataset for distantly supervised relation extraction, Proceedings of the Annual Meeting of the Association for Computational Linguistics, (2021); Bian J., Huang L., Huang X., Zhou H., Zhu S., Grantrel: Grant information extraction via joint entity and relation extraction, Proceedings of the ACL-IJCNLP, pp. 2674-2685, (2021); Bizer C., Lehmann J., Kobilarov G., Auer S., Becker C., Cyganiak R., Hellmann S., Dbpedia-a crystallization point for the web of data, Journal of Web Semantics, 7, 3, pp. 154-165, (2009); Bollacker K., Evans C., Paritosh P., Sturge T., Taylor J., Freebase: A collaboratively created graph database for structuring human knowledge, Proceedings of the 2008 ACM SIGMOD International Conference on Management of Data, pp. 1247-1250, (2008); Brown T., Mann B., Ryder N., Subbiah M., Kaplan J.D., Dhariwal P., Neelakantan A., Shyam P., Sastry G., Askell A., Language models are few-shot learners, Advances in Neural Information Processing Systems, 33, pp. 1877-1901, (2020); Cabot P.-L.H., Navigli R., REBEL: Relation extraction by end-to-end language generation, Findings of the Association for Computational Linguistics: EMNLP, pp. 2370-2381, (2021); Cai D., Lam W., Graph transformer for graph-to-sequence learning, Proceedings of the AAAI Conference on Artificial Intelligence, (2019); Cai R., Zhang X., Wang H., Bidirectional recurrent convolutional neural network for relation classification, Proceedings of the 54th Annual Meeting of the Association for Computational Linguistics (Volume 1: Long Papers), pp. 756-765, (2016); Chalkidis I., Fergadiotis M., Malakasiotis P., Aletras N., Androutsopoulos I., Legal-bert: The muppets straight out of law school, Proceedings of the EMNLP, (2020); Chan Y.S., Roth D., Exploiting syntactico-semantic structures for relation extraction, Proceedings of the 49th Annual Meeting of the Association for Computational Linguistics: Human Language Technologies, pp. 551-560, (2011); Chen H., Hong P., Han W., Majumder N., Poria S., Dialogue relation extraction with document-level heterogeneous graph attention networks, Cognitive Computation, 15, 2, pp. 793-802, (2023); Chen X., Zhang N., Li L., Deng S., Tan C., Xu C., Huang F., Si L., Chen H., Hybrid transformer with multi-level fusion for multimodal knowledge graph completion, Proceedings of the 45th International ACM SIGIR Conference on Research and Development in Information Retrieval, pp. 904-915, (2022); Chen X., Zhang N., Xie X., Deng S., Yao Y., Tan C., Huang F., Si L., Chen H., Knowprompt: Knowledge-aware prompt-tuning with synergistic optimization for relation extraction, Proceedings of the ACM Web Conference, pp. 2778-2788, (2022); Chen Y., Gantt W., Gu W., Chen T., White A.S., Van Durme B., Iterative document-level information extraction via imitation learning, Proceedings of the 17th Conference of the European Chapter of the Association for Computational Linguistics, pp. 1858-1874, (2022); Chen Y., Sun Y., Yang Z., Lin H., Joint entity and relation extraction for legal documents with legal feature enhancement, Proceedings of the International Conference on Computational Linguistics, (2020); Chen Y., Zhang Y., Hu C., Huang Y., Jointly extracting explicit and implicit relational triples with reasoning pattern enhanced binary pointer network, Proceedings of the ACL, pp. 5694-5703, (2021); Chen Y., Zhang Y., Huang Y., Learning reasoning patterns for relational triple extraction with mutual generation of text and graph, Proceedings of the ACL, pp. 1638-1647, (2022); Chen Y., Zhang Y., Huang Y., Learning reasoning patterns for relational triple extraction with mutual generation of text and graph, Findings of the Association for Computational Linguistics: ACL, (2022); Chen Z.-Y., Chang C.-H., Chen Y.-P., Nayak J., Ku L.-W., UHop: An unrestricted-hop relation extraction framework for knowledge-based question answering, Proceedings of the 2019 Conference of the North American Chapter of the Association for Computational Linguistics: Human Language Technologies, Volume, 1, pp. 345-356, (2019); Choi S.-P., Extraction of protein-protein interactions (PPIs) from the literature by deep convolutional neural networks with various feature embeddings, Journal of Information Science, 44, 1, pp. 60-73, (2018); Christopoulou F., Miwa M., Ananiadou S., Connecting the Dots: Document-level neural relation extraction with edge-oriented graphs, Proceedings of the 2019 Conference on Empirical Methods in Natural Language Processing and the 9th International Joint Conference on Natural Language Processing (EMNLP-IJCNLP), pp. 4925-4936, (2019); Christopoulou F., Miwa M., Ananiadou S., Connecting the Dots: Document-level neural relation extraction with edge-oriented graphs, Proceedings of the Conference on Empirical Methods in Natural Language Processing, (2019); Dai Q., Heinzerling B., Inui K., Cross-stitching text and knowledge graph encoders for distantly supervised relation extraction, Proceedings of the Conference on Empirical Methods in Natural Language Processing, (2022); Dai Q., Inoue N., Reisert P., Takahashi R., Inui K., Distantly supervised biomedical knowledge acquisition via knowledge graph based attention, Proceedings of the Workshop on Extracting Structured Knowledge from Scientific Publications, pp. 1-10, (2019); Cui M., Li L., Wang Z., You M., A survey on relation extraction, Knowledge Graph and Semantic Computing. Language, Knowledge, and Intelligence: Second China Conference (CCKS‚Äô17), pp. 50-58, (2017); Deusser T., Ali S.M., Hillebrand L., Nurchalifah D., Jacob B., Bauckhage C., Sifa R., KPI-EDGAR: A novel dataset and accompanying metric for relation extraction from financial documents, 21st IEEE International Conference on Machine Learning and Applications (ICMLA‚Äô22), pp. 1654-1659, (2022); Devlin J., Chang M.-W., Lee K., Toutanova K., Bert: Pre-training of deep bidirectional transformers for language understanding, Proceedings of the 2019 Conference of the North American Chapter of the Association for Computational Linguistics: Human Language Technologies, 1, pp. 4171-4186, (2018); Ding N., Wang X., Fu Y., Xu G., Wang R., Xie P., Shen Y., Huang F., Zheng H.-T., Zhang R., Prototypical representation learning for relation extraction, Proceedings of the International Conference on Learning Representations, (2020); Dixit K., Al-Onaizan Y., Span-level model for relation extraction, Proceedings of the Annual Meeting of the Association for Computational Linguistics, (2019); Doddington G.R., Mitchell A., Przybocki M., Ramshaw L., Strassel S., Weischedel R., The automatic content extraction (ACE) program‚Äìtasks, data, and evaluation, Proceedings of the Fourth International Conference on Language Resources and Evaluation (LREC‚Äô04), (2004); Dong M., Pan C., Luo Z., MapRE: An effective semantic mapping approach for low-resource relation extraction, Proceedings of the 2021 Conference on Empirical Methods in Natural Language Processing, pp. 2694-2704, (2021); Dong Q., Li L., Dai D., Zheng C., Wu Z., Chang B., Sun X., Xu J., Sui Z., A survey for in-context learning, (2022); Du J., Han J., Way A., Wan D., Multi-level structured self-attentions for distantly supervised relation extraction, Proceedings of the 2018 Conference on Empirical Methods in Natural Language Processing, pp. 2216-2225, (2018); Eberts M., Ulges A., Span-based joint entity and relation extraction with transformer pre-training, (ECAI‚Äô20), pp. 2006-2013, (2019); Eberts M., Ulges A., Span-based joint entity and relation extraction with transformer pre-training, Proceedings of the ECAI 2020, (2020); Faruqui M., Kumar S., Multilingual open relation extraction using cross-lingual projection, Proceedings of the 2015 Conference of the North American Chapter of the Association for Computational Linguistics: Human Language Technologies, pp. 1351-1356, (2015); Gao T., Fisch A., Chen D., Making pre-trained language models better few-shot learners, Proceedings of the 59th Annual Meeting of the Association for Computational Linguistics and the 11th International Joint Conference on Natural Language Processing (Volume 1: Long Papers), pp. 3816-3830, (2021); Gao T., Han X., Liu Z., Sun M., Hybrid attention-based prototypical networks for noisy few-shot relation classification, Proceedings of the AAAI Conference on Artificial Intelligence, pp. 6407-6414, (2019); Gao T., Han X., Zhu H., Liu Z., Li P., Sun M., Zhou J., FewRel 2.0: Towards more challenging few-shot relation classification, Proceedings of the EMNLP-IJCNLP, (2019); Gardent C., Shimorina A., Narayan S., Perez-Beltrachini L., Creating training corpora for nlg micro-planning, Proceedings of the 55th Annual Meeting of the Association for Computational Linguistics (ACL), (2017); Gou Y., Lei Y., Liu L., Zhang P., Peng X., A dynamic parameter enhanced network for distant supervised relation extraction, Knowledge-Based Systems, 197, (2020); Gu J., Qian L., Zhou G., Chemical-induced disease relation extraction with various linguistic features, (2016); Gu Y., Tinn R., Cheng H., Lucas M., Usuyama N., Liu X., Naumann T., Gao J., Poon H., Domain-specific language model pretraining for biomedical natural language processing, ACM Transactions on Computing for Healthcare, 3, 1, pp. 1-23, (2021); Guo Q., Yang Y., Yan H., Qiu X., Zhang Z., DORE: Document ordered relation extraction based on generative framework, Proceedings of the Conference on Empirical Methods in Natural Language Processing, (2022); Guo Z., Zhang Y., Lu W., Attention guided graph convolutional networks for relation extraction, Proceedings of the 57th Annual Meeting of the Association for Computational Linguistics, pp. 241-251, (2019); Gutierrez B.J., McNeal N., Washington C., Chen Y., Li L., Sun H., Su Y., Thinking about GPT-3 in-context learning for biomedical ie? think again, Findings of the Association for Computational Linguistics (EMNLP‚Äô22), (2022); Han J., Cheng B., Lu W., Exploring task difficulty for few-shot relation extraction, Proceedings of the 2021 Conference on Empirical Methods in Natural Language Processing, pp. 2605-2616, (2021); Han X., Gao T., Lin Y., Peng H., Yang Y., Xiao C., Liu Z., Li P., Sun M., Zhou J., More data, more relations, more context and more openness: A review and outlook for relation extraction, Proceedings of the AACL, (2020); Han X., Zhao W., Ding N., Liu Z., Sun M., Ptr: Prompt tuning with rules for text classification, AI Open, 3, pp. 182-192, (2021); Ul Haq H., Kocaman V., Talby D., Veyseh A.P.B., Dernoncourt F., Nguyen T.H., Lai V.D., Deeper clinical document understanding using relation extraction, Proceedings of the Workshop on Scientific Document Understanding, (2022); Hendrycks D., Burns C., Chen A., Ball S., Cuad: An expert-annotated nlp dataset for legal contract review, (2021); Herrero-Zazo M., Segura-Bedmar I., Martinez P., Declerck T., The DDI corpus: An annotated corpus with pharmacological substances and drug‚Äìdrug interactions, Journal of Biomedical Informatics, 46, 5, pp. 914-920, (2013); Hewlett D., Lacoste A., Jones L., Polosukhin I., Fandrianto A., Han J., Kelcey M., Berthelot D., WikiReading: A novel large-scale language understanding task over wikipedia, Proceedings of the ACL, (2016); Hillebrand L., Deusser T., Dilmaghani T., Kliem B., Loitz R., Bauckhage C., Sifa R., Kpi-bert: A joint named entity recognition and relation extraction model for financial reports, Proceedings of the 2022 26th International Conference on Pattern Recognition (ICPR), pp. 606-612, (2022); Hou Y., Jochim C., Gleize M., Bonin F., Ganguly D., Identification of tasks, datasets, evaluation metrics, and numeric scores for scientific leaderboards construction, Proceedings of the 57th Annual Meeting of the Association for Computational Linguistics, pp. 5203-5213, (2019); Hu X., Wen L., Xu Y., Zhang C., Yu Philip S., SelfORE: Self-supervised relational feature learning for open relation extraction, Proceedings of the 2020 Conference on Empirical Methods in Natural Language Processing (EMNLP), pp. 3673-3682, (2020); Huang Z., Xu W., Yu K., Bidirectional LSTM-CRF models for sequence tagging, (2015); Jabbari A.A., Sauvage O., Zeine H., Chergui H., A french corpus and annotation schema for named entity recognition and relation extraction of financial news, Proceedings of the International Conference on Language Resources and Evaluation, (2020); Jain S., van Zuylen M., Hajishirzi H., Beltagy I., SciREX: A challenge dataset for document-level information extraction, Proceedings of the 58th Annual Meeting of the Association for Computational Linguistics, pp. 7506-7516, (2020); Hu L., Zhang L., Shi C., Nie L., Guan W., Yang C., Improving distantly-supervised relation extraction with joint label embedding, Proceedings of the 2019 Conference on Empirical Methods in Natural Language Processing and the 9th International Joint Conference on Natural Language Processing, pp. 3821-3829, (2019); Ji B., Yu J., Li S., Ma J., Wu Q., Tan Y., Liu H., Span-based joint entity and relation extraction with attention-based span-specific and contextual semantic representations, Proceedings of the 28th International Conference on Computational Linguistics, pp. 88-99, (2020); Ji B., Yu J., Li S., Ma J., Wu Q., Tan Y., Liu H., Span-based Joint Entity and Relation Extraction with Attention-based Span-specific and Contextual Semantic Representations, Proceedings of the International Conference on Computational Linguistics, (2020); Jia R., Wong C., Poon H., Document-level N-ary relation extraction with multiscale representation learning, Proceedings of the ACL, (2019); Jiang P., Lin J., Wang Z., Sun J., Han J., GenRES: Rethinking evaluation for generative relation extraction in the era of large language models, Proceedings of the 2024 Conference of the North American Chapter of the Association for Computational Linguistics: Human Language Technologies (Volume 1: Long Papers), pp. 2820-2837, (2024); Jiang X., He K., He J., Yan G., A new entity extraction method based on machine reading comprehension, (2021); Jiang Z., Xu F.F., Araki J., Neubig G., How can we know what language models know?, Transactions of the Association for Computational Linguistics, 8, pp. 423-438, (2020); Joshi M., Chen D., Liu Y., Weld D.S., Zettlemoyer L., Levy O., SpanBERT: Improving pre-training by representing and predicting spans, Transactions of the Association for Computational Linguistics, 8, pp. 64-77, (2020); Kanjirangat V., Rinaldi F., Enhancing biomedical relation extraction with transformer models using shortest dependency path features and triplet information, Journal of Biomedical Informatics, 122, (2021); Kassner N., Dufter P., Schutze H., Multilingual LAMA: Investigating knowledge in multilingual pretrained language models, Proceedings of the 16th Conference of the European Chapter of the Association for Computational Linguistics: Main, pp. 3250-3258, (2021); Kruiper R., Vincent J., Chen-Burger J., Desmulliez M., Konstas I., In layman‚Äôs terms: Semi-open relation extraction from scientific texts, Proceedings of the 58th Annual Meeting of the Association for Computational Linguistics, pp. 1489-1500, (2020); Lee B., Choi Y.S., Graph based network with contextualized representations of turns in dialogue, Proceedings of the Conference on Empirical Methods in Natural Language Processing, (2021); Lee J., Yoon W., Kim S., Kim D., Kim S., So C.H., Kang J., BioBERT: A pre-trained biomedical language representation model for biomedical text mining, Bioinformatics, 36, 4, pp. 1234-1240, (2020); Lee S., Seo S., Oh B., Lee K.-H., Shin D., Lee Y., Cross-sentence N-ary relation extraction using entity link and discourse relation, Proceedings of the 29th ACM International Conference on Information and Knowledge Management, pp. 705-714, (2020); Lester B., Al-Rfou R., Constant N., The power of scale for parameter-efficient prompt tuning, Proceedings of the 2021 Conference on Empirical Methods in Natural Language Processing, pp. 3045-3059, (2021); Levy O., Seo M., Choi E., Zettlemoyer L., Zero-shot relation extraction via reading comprehension, Proceedings of the 21st Conference on Computational Natural Language Learning (CoNLL 2017), pp. 333-342, (2017); Li B., Ye W., Sheng Z., Xie R., Xi X., Zhang S., Graph enhanced dual attention network for document-level relation extraction, Proceedings of the International Conference on Computational Linguistics, (2020); Li F., Zhang M., Fu G., Ji D., A neural joint model for entity and relation extraction from biomedical text, BMC Bioinformatics, 18, 1, pp. 1-11, (2017); Li X., Luo X., Dong C., Yang D., Luan B., He Z., TDEER: An efficient translating decoding schema for joint extraction of entities and relations, Proceedings of the 2021 Conference on Empirical Methods in Natural Language Processing, pp. 8055-8064, (2021); Li X., Yin F., Sun Z., Li X., Yuan A., Chai D., Zhou M., Li J., Entity-relation extraction as multi-turn question answering, Proceedings of the 57th Annual Meeting of the Association for Computational Linguistics, pp. 1340-1350, (2019); Li X.L., Liang P., Prefix-tuning: Optimizing continuous prompts for generation, Proceedings of the 59th Annual Meeting of the Association for Computational Linguistics and the 11th International Joint Conference on Natural Language Processing (Volume 1: Long Papers), pp. 4582-4597, (2021); Li Y., Long G., Shen T., Zhou T., Yao L., Huo H., Jiang J., Self-attention enhanced selective gate with entity-aware embedding for distantly supervised relation extraction, Proceedings of the AAAI Conference on Artificial Intelligence, pp. 8269-8276, (2020); Liu W., Zhou P., Zhao Z., Wang Z., Ju Q., Deng H., Wang P., K-bert: Enabling language representation with knowledge graph, Proceedings of the AAAI Conference on Artificial Intelligence, pp. 2901-2908, (2020); Liu Y., Hu J., Wan X., Chang T.-H., Learn from relation information: Towards prototype representation rectification for few-shot relation extraction, Findings of the Association for Computational Linguistics: NAACL, pp. 1822-1831, (2022); Liu Y., Ott M., Goyal N., Du J., Joshi M., Chen D., Levy O., Lewis M., Zettlemoyer L., Stoyanov V., Roberta: A robustly optimized bert pretraining approach, (2019); Luan Y., Information extraction from scientific literature for method recommendation, (2018); Luan Y., He L., Ostendorf M., Hajishirzi H., Multi-task identification of entities, relations, and coreference for scientific knowledge graph construction, Proceedings of the 2018 Conference on Empirical Methods in Natural Language Processing, pp. 3219-3232, (2018); Luan Y., He L., Ostendorf M., Hajishirzi H., Multi-task identification of entities, relations, and coreference for scientific knowledge graph construction, Proceedings of the Conference on Empirical Methods in Natural Language Processing, (2018); Luan Y., Wadden D., He L., Shah A., Ostendorf M., Hajishirzi H., A general framework for information extraction using dynamic span graphs, Proceedings of the 2019 Conference of the North American Chapter of the Association for Computational Linguistics: Human Language Technologies, Volume, 1, pp. 3036-3046, (2019); Luo K., Lin F., Luo X., Zhu K., Knowledge base question answering via encoding of complex query graphs, Proceedings of the 2018 Conference on Empirical Methods in Natural Language Processing, pp. 2185-2194, (2018); Ma X., Hovy E., End-to-end sequence labeling via bi-directional lstm-cnns-crf, Proceedings of the 54th Annual Meeting of the Association for Computational Linguistics (Volume 1: Long Papers), pp. 1064-1074, (2016); Magnusson I.H., Friedman S.E., Extracting fine-grained knowledge graphs of scientific claims: Dataset and transformer-based results, Proceedings of the Conference on Empirical Methods in Natural Language Processing, (2021); Mandya A., Bollegala D., Coenen F., Graph convolution over multiple dependency subgraphs for relation extraction, Proceedings of the COLING. International Committee on Computational Linguistics, pp. 6424-6435, (2020); Mikolov T., Chen K., Corrado G., Dean J., Efficient estimation of word representations in vector space, (2013); Mikolov T., Sutskever I., Chen K., Corrado G.S., Dean J., Distributed representations of words and phrases and their compositionality, Advances in Neural Information Processing Systems, 26, (2013); Milosevic N., Thielemann W., Relationship extraction for knowledge graph creation from biomedical literature, (2022); Mintz M., Bills S., Snow R., Jurafsky D., Distant supervision for relation extraction without labeled data, Proceedings of the Joint Conference of the 47th Annual Meeting of the ACL and the 4th International Joint Conference on Natural Language Processing of the AFNLP, pp. 1003-1011, (2009); Miwa M., Bansal M., End-to-end relation extraction using LSTMs on sequences and tree structures, Proceedings of the ACL, (2016); Nan G., Guo Z., Sekulic I., Lu W., Reasoning with latent structure refinement for document-level relation extraction, Proceedings of the 58th Annual Meeting of the Association for Computational Linguistics, pp. 1546-1557, (2020); Nan G., Guo Z., Sekulic I., Lu W., Reasoning with latent structure refinement for document-level relation extraction, Proceedings of the Annual Meeting of the Association for Computational Linguistics, (2020); Nayak T., Majumder N., Goyal P., Poria S., Deep neural approaches to relation triplets extraction: A comprehensive survey, Cognitive Computation, 13, 5, pp. 1215-1232, (2021); Nayak T., Ng H.T., Effective modeling of encoder-decoder architecture for joint entity and relation extraction, Proceedings of the AAAI Conference on Artificial Intelligence, pp. 8528-8535, (2020); Paolini G., Athiwaratkun B., Krone J., Ma J., Achille A., Anubhai R., dos Santos C.N., Xiang B., Soatto S., Structured prediction as translation between augmented natural languages, Proceedings of the International Conference on Learning Representations, (2021); Pawar S., Palshikar G.K., Bhattacharyya P., Relation extraction: A survey, (2017); Peng Y., Yan S., Lu Z., Transfer learning in biomedical natural language processing: An evaluation of BERT and ELMo on ten benchmarking datasets, Proceedings of the 18th BioNLP Workshop and Shared Task, (2019); Pennington J., Socher R., Manning C.D., Glove: Global vectors for word representation, Proceedings of the 2014 Conference on Empirical Methods in Natural Language Processing (EMNLP), pp. 1532-1543, (2014); Peters M.E., Neumann M., Iyyer M., Gardner M., Clark C., Lee K., Zettlemoyer L., Deep contextualized word representations, Proceedings of the 2018 Conference of the North American Chapter of the Association for Computational Linguistics, pp. 2227-2237, (2018); Phi V.-T., Santoso J., Tran V.-H., Shindo H., Shimbo M., Matsumoto Y., Distant supervision for relation extraction via piecewise attention and bag-level contextual inference, IEEE Access, 7, pp. 103570-103582, (2019); Qin G., Eisner J., Learning how to ask: Querying LMs with mixtures of soft prompts, Proceedings of the 2021 Conference of the North American Chapter of the Association for Computational Linguistics: Human Language Technologies, pp. 5203-5212, (2021); Qiu L., Liang Y., Zhao Y., Lu P., Peng B., Yu Z., Wu Y.N., Zhu S.-C., SocAoG: Incremental graph parsing for social relation inference in dialogues, Proceedings of the 59th Annual Meeting of the Association for Computational Linguistics and the 11th International Joint Conference on Natural Language Processing (Volume 1: Long Papers), pp. 658-670, (2021); Qu M., Gao T., Xhonneux L.-P., Tang J., Few-shot relation extraction via bayesian meta-learning on relation graphs, International Conference on Machine Learning, pp. 7867-7876, (2020); Rathore V., Badola K., Singla P., PARE: A simple and strong baseline for monolingual and multilingual distantly supervised relation extraction, Proceedings of the 60th Annual Meeting of the Association for Computational Linguistics Volume, 2, pp. 340-354, (2022); Ren X., Wu Z., He W., Qu M., Voss C.R., Ji H., Abdelzaher T.F., Han J., Cotype: Joint extraction of typed entities and relations with knowledge bases, Proceedings of the 26th International Conference on World Wide Web, pp. 1015-1024, (2017); Ribeiro M.T., Singh S., Guestrin C., Why should i trust you?‚Äù Explaining the predictions of any classifier, Proceedings of the 22nd ACM SIGKDD International Conference on Knowledge Discovery and Data Mining, pp. 1135-1144, (2016); Riedel S., Yao L., McCallum A., Modeling relations and their mentions without labeled text, Proceedings of the Joint European Conference on Machine Learning and Knowledge Discovery in Databases, (2010); Roy A., Pan S., Incorporating medical knowledge in BERT for clinical relation extraction, Proceedings of the EMNLP, (2021); Roy A., Pan S., Incorporating medical knowledge in BERT for clinical relation extraction, Proceedings of the Conference on Empirical Methods in Natural Language Processing, (2021); Saeed W., Omlin C., Explainable AI (XAI): A systematic meta-survey of current challenges and future opportunities, Knowledge-Based Systems, 263, (2023); Sahu S.K., Christopoulou F., Miwa M., Ananiadou S., Inter-sentence relation extraction with document-level graph convolutional neural network, Proceedings of the 57th Annual Meeting of the Association for Computational Linguistics, pp. 4309-4316, (2019); Sainz O., de Lacalle O.L., Labaka G., Barrena A., Agirre E., Label verbalization and entailment for effective zero and few-shot relation extraction, Proceedings of the 2021 Conference on Empirical Methods in Natural Language Processing, pp. 1199-1212, (2021); Santosh T., Chakraborty P., Dutta S., Sanyal D.K., Das P.P., Joint entity and relation extraction from scientific documents: Role of linguistic information and entity types, EEKE@ JCDL, 21, pp. 15-19, (2021); Sarrouti M., Tao C., Randriamihaja Y.M., Comparing encoder-only and encoder-decoder transformers for relation extraction from biomedical texts: An empirical study on ten benchmark datasets, Proceedings of the BIONLP, (2022); Schick T., Schmid H., Schutze H., Automatically identifying words that can serve as labels for few-shot text classification, Proceedings of the 28th International Conference on Computational Linguistics, pp. 5569-5578, (2020); Schick T., Schutze H., Exploiting cloze-questions for few-shot text classification and natural language inference, Proceedings of the 16th Conference of the European Chapter of the Association for Computational Linguistics: Main, pp. 255-269, (2021); Seganti A., Firlag K., Skowronska H., Satlawa M., Andruszkiewicz P., Multilingual entity and relation extraction dataset and model, Proceedings of the ACL, (2021); Shang Y., Huang H.-Y., Mao X.-L., Sun X., Wei W., Are noisy sentences useless for distant supervised relation extraction?, Proceedings of the AAAI Conference on Artificial Intelligence, pp. 8799-8806, (2020); Shang Y.-M., Huang H., Sun X., Wei W., Mao X.-L., Learning relation ties with a force-directed graph in distant supervised relation extraction, ACM Transactions on Information Systems, 41, 1, pp. 1-23, (2023); Sharma S., Nayak T., Bose A., Meena A.K., Dasgupta K., Ganguly N., Goyal P., FinRED: A dataset for relation extraction in financial domain, Companion Proceedings of the Web Conference, pp. 595-597, (2022); Shen Y., Huang X.-J., Attention-based convolutional neural network for semantic relation extraction, Proceedings of COLING 2016, the 26th International Conference on Computational Linguistics: Technical Papers, pp. 2526-2536, (2016); Shen Y., Ma X., Tang Y., Lu W., A trigger-sense memory flow framework for joint entity and relation extraction, Proceedings of the Web Conference, pp. 1704-1715, (2021); Shin T., Razeghi Y., Robert L., Logan I.V., Wallace E., Singh S., AutoPrompt: Eliciting knowledge from language models with automatically generated prompts, Proceedings of the 2020 Conference on Empirical Methods in Natural Language Processing (EMNLP), pp. 4222-4235, (2020); Soares L.B., Fitzgerald N., Ling J., Kwiatkowski T., Matching the blanks: Distributional similarity for relation learning, Proceedings of the 57th Annual Meeting of the Association for Computational Linguistics, pp. 2895-2905, (2019); Socher R., Huval B., Manning C.D., Ng A.Y., Semantic compositionality through recursive matrix-vector spaces, Proceedings of the 2012 Joint Conference on Empirical Methods in Natural Language Processing and Computational Natural Language Learning, pp. 1201-1211, (2012); Son J., Kim J., Lim J.H., Lim H.-J., GRASP: Guiding model with relational semantics using prompt for dialogue relation extraction, Proceedings of the International Conference on Computational Linguistics, (2022); Song W., Zhou X., Yang P., Sun Y., Yang L., Lin H., Joint entity and relation extraction for legal texts, Proceedings of the 20th Chinese National Conference on Computational Linguistics, pp. 589-599, (2021); Subburathinam A., Lu D., Ji H., May J., Chang S.-F., Sil A., Voss C., Cross-lingual structure transfer for relation and event extraction, Proceedings of the 2019 Conference on Empirical Methods in Natural Language Processing and the 9th International Joint Conference on Natural Language Processing (EMNLP-IJCNLP), pp. 313-325, (2019); Sui D., Zeng X., Chen Y., Liu K., Zhao J., Joint entity and relation extraction with set prediction networks, IEEE Transactions on Neural Networks and Learning Systems, (2023); Sun K., Zhang R., Mensah S., Mao Y., Liu X., Recurrent interaction network for jointly extracting entities and classifying relations, Proceedings of the 2020 Conference on Empirical Methods in Natural Language Processing (EMNLP), pp. 3722-3732, (2020); Sun Q., Huang K., Yang X., Tong R., Zhang K., Poria S., Consistency guided knowledge retrieval and denoising in LLMs for zero-shot document-level relation triplet extraction, Proceedings of the ACM on Web Conference, pp. 4407-4416, (2024); Taille B., Guigue V., Scoutheeten G., Gallinari P., Let‚Äôs stop incorrect comparisons in end-to-end relation extraction!, Proceedings of the 2020 Conference on Empirical Methods in Natural Language Processing (EMNLP), pp. 3689-3701, (2020); Tan X., Pergola G., He Y., Extracting event temporal relations via hyperbolic geometry, Proceedings of the 2021 Conference on Empirical Methods in Natural Language Processing, pp. 8065-8077, (2021); Tang W., Xu B., Zhao Y., Mao Z., Liu Y., Liao Y., Xie H., UniRel: Unified representation and interaction for joint relational triple extraction, Proceedings of the 2022 Conference on Empirical Methods in Natural Language Processing, pp. 7087-7099, (2022) | AC3: X. Zhao; The Chinese University of Hong Kong, Hong Kong, Hong Kong; email: xzhao@se.cuhk.edu.hk; M. Yang; Shenzhen Institutes of Advanced Technology, Chinese Academy of Sciences, Shenzhen, Guangdong, China; email: min.yang@siat.ac.cn; Y. Shen; Sun Yat-Sen University, Shenzhen, Guangdong, China; email: sheny76@mail.sysu.edu.cn | AE3: Association for Computing Machinery | AK3: 3600300 | AM3: ACSUE | AO3: English | AP3: ACM Comput Surv | AQ3: Article | AR3: Final | AS3: All Open Access; Bronze Open Access | AT3: Scopus | AU3: 2-s2.0-85200560529 | AV3: q1 | AW3: Scopus | AX3: ? | AY3: =IF(AX3=TRUE,1,IF(AX3=FALSE,0,-1)) -> -1 | AZ3: ? | BA3: =IF(AZ3=TRUE,1,IF(AZ3=FALSE,0,-1)) -> -1 | BB3: TRUE | BC3: =IF(BB3=TRUE,1,IF(BB3=FALSE,0,-1)) -> 1 | BD3: 1 | BE3: 1 | BF3: 1 | BG3: 1 | BH3: =IF(BG3=1,"Yes",IF(BG3=-1,"Doubt","No")) -> Yes | BI3: =IF(BF3=1,"Yes","No") -> Yes | BJ3: 1 | BK3: Survey on RE. It exposes Triplet extaction also.
A4: 68 | B4: Theptakob N.; Seneewong Na Ayutthaya T.; Saetia C.; Chalothorn T.; Buabthong P. | C4: Theptakob, Nathanon (58628626400); Seneewong Na Ayutthaya, Thititorn (57209280649); Saetia, Chanatip (57204899037); Chalothorn, Tawunrat (56523303800); Buabthong, Pakpoom (57195431698) | D4: 58628626400; 57209280649; 57204899037; 56523303800; 57195431698 | E4: A Cross-Document Coreference Resolution Approach to Low-Resource Languages | F4: 2023.0 | G4: Lecture Notes in Computer Science (including subseries Lecture Notes in Artificial Intelligence and Lecture Notes in Bioinformatics) | H4: 14118 LNAI | K4: 422.0 | L4: 431.0 | M4: 9.0 | N4: 0.0 | O4: 10.1007/978-3-031-40286-9_34 | P4: https://www.scopus.com/inward/record.uri?eid=2-s2.0-85173034493&doi=10.1007%2f978-3-031-40286-9_34&partnerID=40&md5=628290bc59a106c13715816e904ac145 | Q4: Kasikorn Business-Technology Group, Nonthaburi, Thailand; Nakhon Ratchasima Rajabhat University, Nakhon Ratchasima, Thailand | R4: Theptakob N., Kasikorn Business-Technology Group, Nonthaburi, Thailand; Seneewong Na Ayutthaya T., Kasikorn Business-Technology Group, Nonthaburi, Thailand; Saetia C., Kasikorn Business-Technology Group, Nonthaburi, Thailand; Chalothorn T., Kasikorn Business-Technology Group, Nonthaburi, Thailand; Buabthong P., Kasikorn Business-Technology Group, Nonthaburi, Thailand, Nakhon Ratchasima Rajabhat University, Nakhon Ratchasima, Thailand | S4: Coreference resolution is an important area of research in natural language processing that deals with the task of identifying and grouping all the expressions in a text that refer to the same entity. This work presents a system to improve and develop a coreference resolution model for Thai language, based on the existing English clustering-based model. Specifically, we introduce a method to convert Thai text into ECB + -equivalent datasets, which can be used as benchmark for the Thai language. This paper follows an existing model trained for English coreference resolution which uses agglomerative clustering to segment clusters of coreference entities across document. The model trained and evaluated using our data achieves the best CoNLL F1 score of 72.87. Finally, we present a comparative study of the effect of manual and automatic span extractors on Thai language model performance. The results of our study indicate that our proposed pipeline, which utilizes the fine-tuned longformer model as the encoder, offers a viable alternative to more complex and resource-intensive methods. Our work also suggests that the use of existing NER and entity recognizer models can help automate span annotation prior to the subsequent conference clustering module. This study offers a potential framework for the construction of coreference resolution models in other low-resource languages. ¬© 2023, The Author(s), under exclusive license to Springer Nature Switzerland AG. | T4: Clustering; Coreference resolution; Cross-document relation extraction; Entity alignment; Knowledge graph construction | U4: Natural language processing systems; Clusterings; Coreference resolution; Cross documents; Cross-document relation extraction; Document relations; Entity alignment; Graph construction; Knowledge graph construction; Knowledge graphs; Relation extraction; Knowledge graph | AB4: Wang T., Li H., Coreference resolution improves educational knowledge graph construction, ICKG, (2020); Sukthanker R., Poria S., Cambria E., Thirunavukarasu R., Anaphora and coreference resolution: A review, Inform. Fusion, 59, pp. 139-162, (2020); Deng Y., Recommender systems based on graph embedding techniques: A review, IEEE Access, (2022); Khongcharoen W., Saetia C., Chalothorn T., Buabthong P., Question answering over knowledge graphs for thai retail banking products, Isai-Nlp. IEEE, (2022); Cattan A., Eirew A., Stanovsky G., Joshi M., Dagan I., Cross-document coreference resolution over predicted mentions, ACL, (2021); Keshtkaran A., Yuhaniz S.S., Ibrahim S., An overview of cross-document coreference resolution, Iconda, (2017); Rahimian F., Girdzijauskas S., Haridi S., Parallel community detection for cross-document coreference, IEEE WI, (2014); Culotta A., Wick M., McCallum A., First-Order Probabilistic Models for Coreference Resolution, (2007); Baron A., Freedman M., Who is who and what is what: Experiments in cross-document co-reference, EMNLP, (2008); Syed Z.S., Finin T., Joshi A., Wikitology: Using Wikipedia as an Ontology, (2008); Xue Z., Li R., Dai Q., Jiang Z., Corefdre: Document-Level Relation Extraction with Coreference Resolution, (2022); Cybulska P.V.A., Using a Sledgehammer to Crack a Nut? Lexical Diversity and Event Coreference Resolution, (2014); Moosavi N.S., Strube M., Which coreference evaluation metric do you trust? a proposal for a link-based entity aware metric, In ACL, (2016); Kongwan A., Kamaruddin S.S., Ahmad F.K., anaphora resolution in Thai EDU segmentation, J. Comput. Sci., 18, pp. 306-315, (2022); Phatthiyaphaibun W., Chaovavanich K., Polpanumas C., Suriyawongkul A., Lowphansirikul L., Chormai P., PyThaiNLP: Thai natural language processing in python, Zenodo, (2016); Klie J.-C., Bugert M., Boullosa B., de Castilho R.E., Gurevych I., The Inception Platform: Machine-Assisted and Knowledge-Oriented Interactive Annotation, (2018); Conneau A., Khandelwal K., Goyal N., Chaudhary V., Wenzek G., Guzman F., Et Al: Unsupervised Cross-Lingual Representation Learning at Scale, (2019); Lowphansirikul L., Polpanumas C., Jantrakulchai N., Nutanong S., Wangchanberta: Pretraining Transformer-Based Thai Language Models, Arxiv, 2101, (2021); Buaphet W., Udomcharoenchaikit C., Limkonchotiwat P., Rutherford A., Nutanong S., Thai nested named entity recognition corpus, ACL, (2022); Wang C., Liu X., Chen Z., Hong H., Tang J., Song D., DeepStruct: Pretraining of language models for structure prediction, ACL, (2022); Liu Y., Ott M., Goyal N., Du J., Joshi M., Chen D., Et al., Roberta: A Robustly Optimized BERT Pretraining Approach. Arxiv, 1907, (2019) | AC4: P. Buabthong; Nakhon Ratchasima Rajabhat University, Nakhon Ratchasima, Thailand; email: pakpoom.b@nrru.ac.th | AD4: Jin Z.; Jiang Y.; Ma W.; Buchmann R.A.; Ghiran A.-M.; Bi Y. | AE4: Springer Science and Business Media Deutschland GmbH | AG4: Knowledge Science, Engineering and Management - 16th International Conference, KSEM 2023, Proceedings | AH4: 16 August 2023 through 18 August 2023 | AI4: Guangzhou | AJ4: 299379.0 | AK4: 3029743 | AL4: 978-303140285-2 | AO4: English | AP4: Lect. Notes Comput. Sci. | AQ4: Conference paper | AR4: Final | AT4: Scopus | AU4: 2-s2.0-85173034493 | AV4: q1 | AW4: Scopus | AX4: TRUE | AY4: =IF(AX4=TRUE,1,IF(AX4=FALSE,0,-1)) -> 1 | AZ4: TRUE | BA4: =IF(AZ4=TRUE,1,IF(AZ4=FALSE,0,-1)) -> 1 | BB4: ? | BC4: =IF(BB4=TRUE,1,IF(BB4=FALSE,0,-1)) -> -1 | BD4: 1 | BE4: 1 | BF4: 0 | BG4: 0 | BH4: =IF(BG4=1,"Yes",IF(BG4=-1,"Doubt","No")) -> No | BI4: =IF(BF4=1,"Yes","No") -> No | BJ4: 0 | BK4: Relation clustering to perform coreference resolution applied to entities.
A5: 143 | B5: Gou Y.; Zhang Y.; Zhu J.; Shu Y. | C5: Gou, Yuxiao (58984248200); Zhang, Yiping (57194787768); Zhu, Jian (57207355370); Shu, Yidan (57721411300) | D5: 58984248200; 57194787768; 57207355370; 57721411300 | E5: A document-level information extraction pipeline for layered cathode materials for sodium-ion batteries | F5: 2024.0 | G5: Scientific Data | H5: 11 | I5: 1.0 | J5: 372.0 | N5: 0.0 | O5: 10.1038/s41597-024-03196-1 | P5: https://www.scopus.com/inward/record.uri?eid=2-s2.0-85190269909&doi=10.1038%2fs41597-024-03196-1&partnerID=40&md5=eb04088f90531a244a936dc1db128385 | Q5: School of Materials Science and Engineering, Sun Yat-sen University, Guangdong, China; The Key Laboratory of Low-carbon Chemistry & amp; Energy Conservation of Guangdong Province, Guangdong, China | R5: Gou Y., School of Materials Science and Engineering, Sun Yat-sen University, Guangdong, China; Zhang Y., School of Materials Science and Engineering, Sun Yat-sen University, Guangdong, China; Zhu J., School of Materials Science and Engineering, Sun Yat-sen University, Guangdong, China; Shu Y., School of Materials Science and Engineering, Sun Yat-sen University, Guangdong, China, The Key Laboratory of Low-carbon Chemistry & amp; Energy Conservation of Guangdong Province, Guangdong, China | S5: Natural language processing techniques enable extraction of valuable information from large amounts of published literature for the application of data science and technology, i.e. machine learning in the field of materials science. Nevertheless, the automated extraction of data from full-text documents remains a complex task. We propose a document-level natural language processing pipeline for literature extraction of comprehensive information on layered cathode materials for sodium-ion batteries. The pipeline enhances entity recognition with contextual supplementary information while capturing the article structure. Finally, a heuristic multi-level relationship extraction algorithm is employed in relation extraction to extract experimental parameters and complex performance relationships respectively. We successfully extracted a comprehensive dataset containing 5265 records from 1747 documents, encompassing essential information such as chemical composition, synthesis parameters, and electrochemical properties. By implementing our pipeline, we have made significant progress in overcoming the challenges associated with data scarcity in battery informatics. The extracted datasets provide a valuable resource for further research and development in the field of layered cathode materials. ¬© The Author(s) 2024. | U5: Algorithms; Data Science; Electric Power Supplies; Electrodes; Information Storage and Retrieval; algorithm; data science; information retrieval; power supply | Z5: Basic and Applied Basic Research Foundation of Guangdong Province, (202201011269); Basic and Applied Basic Research Foundation of Guangdong Province | AA5: The study was supported by Guangzhou Basic and Applied Basic Research Foundation (grant references: 202201011269). The authors would like to extend their gratitude to the anonymous reviewers whose constructive comments greatly helped in the improvement of the article. | AB5: Oz E., Altin S., Avci S., Tunnel/Layer Composite Na<sub>0.44</sub>MnO<sub>2</sub> Cathode Material with Enhanced Structural Stability via Cobalt Doping for Sodium-Ion Batteries, ACS Omega, 8, pp. 27170-27178, (2023); Peng B., Et al., Regulating the local chemical environment in layered O3-NaNi0.5Mn0.5O2 achieves practicable cathode for sodium-ion batteries, Energy Storage Materials, 56, pp. 631-641, (2023); Liu Y., Et al., Isostructural Synthesis of Iron‚ÄêBased Prussian Blue Analogs for Sodium‚ÄêIon Batteries, Small, 19, (2023); Sun R., Et al., Substituting inert phosphate with redox-active silicate towards advanced polyanion-type cathode materials for sodium-ion batteries, Nanoscale, 15, pp. 3345-3350, (2023); Ling C., A review of the recent progress in battery informatics, npj Computational Materials, 8, (2022); Wang W., Et al., Automated pipeline for superalloy data by text mining, npj Computational Materials, 8, (2022); Shetty P., Et al., A general-purpose material property data extraction pipeline from large polymer corpora using natural language processing, npj Computational Materials, 9, (2023); Yan R., Jiang X., Wang W., Dang D., Su Y., Materials information extraction via automatically generated corpus, Scientific Data, 9, (2022); Kim E., Et al., Materials Synthesis Insights from Scientific Literature via Text Extraction and Machine Learning, Chemistry of Materials, 29, pp. 9436-9444, (2017); Vaswani A., Et al., Attention is all you need, Adv Neural Inf Process Syst, 30, (2017); In Association for Computational Linguistics, pp. 3615-3620; Huang S., Cole J.M., BatteryBERT: A Pretrained Language Model for Battery Database Enhancement, Journal of Chemical Information and Modeling, 62, pp. 6365-6377, (2022); Sivan D., Et al., Advances in materials informatics: a review, Journal of Materials Science, 59, pp. 2602-2643, (2024); Olivetti E.A., Et al., Data-driven materials research enabled by natural language processing and information extraction, Applied Physics Reviews, 7, (2020); Isazawa T., Cole J.M., Single Model for Organic and Inorganic Chemical Named Entity Recognition in ChemDataExtractor, Journal of Chemical Information and Modeling, 62, pp. 1207-1213, (2022); El-Bousiydy H., Et al., What Can Text Mining Tell Us About Lithium-Ion Battery Researchers‚Äô, Habits? Batteries & Supercaps, 4, pp. 758-766, (2021); Kononova O., Et al., Text-mined dataset of inorganic materials synthesis recipes, Scientific Data, 6, (2019); Huang S., Cole J.M., A database of battery materials auto-generated using ChemDataExtractor, Scientific Data, 7, (2020); Kononova O., Et al., Opportunities and challenges of text mining in materials research, iScience, 24, (2021); Liao Z., Fei J., Zeng W., Zhao X., Few-shot named entity recognition with hybrid multi-prototype learning, World Wide Web, 26, pp. 2521-2544, (2023); Schwartz A.S., Hearst M.A., A Simple Algorithm for Identifying Abbreviation Definitions in Biomedical Text, Pacific Symposium on Biocomputing. Pacific Symposium on Biocomputing, pp. 451-462, (2002); Shi C., Et al., Challenges of layer-structured cathodes for sodium-ion batteries, Nanoscale Horiz, 7, pp. 338-351, (2022); Guo S., Et al., Cation-mixing stabilized layered oxide cathodes for sodium-ion batteries, Science Bulletin, 63, pp. 376-384, (2018); Takanobu R., Zhang T., Liu J., Huang M., A Hierarchical Framework for Relation Extraction with Reinforcement Learning, Proceedings of the AAAI Conference on Artificial Intelligence, 33, pp. 7072-7079, (2019); McDonald R., Et al., In Proceedings of the 43Rd Annual Meeting on Association for Computational Linguistics, pp. 491-498, (2005); Bach N., Badaskar S., A Review of Relation Extraction, Lit. Rev. Lang. Stat, 2, pp. 1-15, (2007); Tang K., Et al., Electrochemical performance and structural stability of air-stable Na0.67Ni0.33Mn0.67-xTixO2 cathode materials for high-performance sodium-ion batteries, Chemical Engineering Journal, 399, (2020); Jiang X., Et al., Tunnel-structured Na<sub>0.54</sub>Mn<sub>0.50</sub>Ti<sub>0.51</sub>O<sub>2</sub> and Na<sub>0.54</sub>Mn<sub>0.50</sub>Ti<sub>0.51</sub>O<sub>2</sub>/C nanorods as advanced cathode materials for sodium-ion batteries, Chemical Communications, 51, pp. 8480-8483, (2015); Xu X., Ji S., Gao R., Liu J., Facile synthesis of P2-type Na<sub>0.4</sub>Mn<sub>0.54</sub>Co<sub>0.46</sub>O<sub>2</sub>as a high capacity cathode material for sodium-ion batteries, RSC Advances, 5, pp. 51454-51460, (2015); Ramasamy H.V., Et al., Cu-doped P2-Na<sub>0.5</sub>Ni<sub>0.33</sub>Mn<sub>0.67</sub>O<sub>2</sub> encapsulated with MgO as a novel high voltage cathode with enhanced Na-storage properties, Journal of Materials Chemistry A, 5, pp. 8408-8415, (2017); Zhang J., Yu D.Y.W., Stabilizing Na<sub>0.7</sub>MnO<sub>2</sub> cathode for Na-ion battery via a single-step surface coating and doping process, Journal of Power Sources, 391, pp. 106-112, (2018); Zhao Y., Et al., A review on modeling of electro-chemo-mechanics in lithium-ion batteries, Journal of Power Sources, 413, pp. 259-283, (2019); Zhou D., Et al., Operando X-ray absorption spectroscopy investigations on Na x Ni 1/3 Fe 1/3 Mn 1/3 O 2 positive electrode materials for sodium and sodium ion batteries, Journal of Power Sources, 473, (2020); Deng Q., Et al., Nanoscale surface modification of P2-type Na 0.65 [Mn 0.70 Ni 0.16 Co 0.14]O 2 cathode material for high-performance sodium-ion batteries, Chemical Engineering Journal, 404, (2021); Li W., Et al., Building superior layered oxide cathode via rational surface engineering for both liquid & solid-state sodium ion batteries, Chemical Engineering Journal, 421, (2021); Voronina N., Kim H.J., Shin M., Myung S.-T., Rational design of Co-free layered cathode material for sodium-ion batteries, Journal of Power Sources, 514, (2021); Wei T.-T., Liu X., Yang S.-J., Wang P.-F., Yi T.-F., Regulating the electrochemical activity of Fe-Mn-Cu-based layer oxides as cathode materials for high-performance Na-ion battery, Journal of Energy Chemistry, 80, pp. 603-613, (2023); Wang Q.-C., Et al., Tuning P2-Structured Cathode Material by Na-Site Mg Substitution for Na-Ion Batteries, Journal of the American Chemical Society, 141, pp. 840-848, (2018); Ma C., Et al., Stacking Order Induced Anion Redox Regulation for Layer‚ÄêStructured Na 0.75 Li 0.2 Mn 0.7 Cu 0.1 O 2 Cathode Materials, Small, 19, (2023); Hwang J.-Y., Et al., Radially aligned hierarchical columnar structure as a cathode material for high energy density sodium-ion batteries, Nature Communications, 6, (2015); Mu L., Et al., Prototype Sodium‚ÄêIon Batteries Using an Air‚ÄêStable and Co/Ni‚ÄêFree O3‚ÄêLayered Metal Oxide Cathode, Advanced Materials, 27, pp. 6928-6933, (2015); Feng J., Et al., Properties of the ‚ÄúZ‚Äù‚ÄêPhase in Mn‚ÄêRich P2‚ÄêNa 0.67 Ni 0.1 Mn 0.8 Fe 0.1 O 2 as Sodium‚ÄêIon‚ÄêBattery Cathodes, Small, 19, (2023); Yang J., Et al., O3‚ÄêType Layered Ni‚ÄêRich Oxide: A High‚ÄêCapacity and Superior‚ÄêRate Cathode for Sodium‚ÄêIon Batteries, Small, 15, (2019); Shi Q., Et al., Niobium-doped layered cathode material for high-power and low-temperature sodium-ion batteries, Nature Communications, 13, (2022); Yang L., Et al., Lithium-Doping Stabilized High-Performance P2‚ÄìNa<sub>0.66</sub>Li<sub>0.18</sub>Fe<sub>0.12</sub>Mn<sub>0.7</sub>O<sub>2</sub> Cathode for Sodium Ion Batteries, Journal of the American Chemical Society, 141, pp. 6680-6689, (2019); Sun L., Et al., Insight into Ca‚ÄêSubstitution Effects on O3‚ÄêType NaNi 1/3 Fe 1/3 Mn 1/3 O 2 Cathode Materials for Sodium‚ÄêIon Batteries Application, Small, 14, (2018); Ren M., Et al., Homeostatic Solid Solution in Layered Transition-Metal Oxide Cathodes of Sodium-Ion Batteries, Journal of the American Chemical Society, 145, pp. 224-233, (2022); Xiao Y., Et al., Formulating High‚ÄêRate and Long‚ÄêCycle Heterostructured Layered Oxide Cathodes by Local Chemistry and Orbital Hybridization Modulation for Sodium‚ÄêIon Batteries, Advanced Materials, 34, (2022); Ma C., Et al., Exploring Oxygen Activity in the High Energy P2-Type Na<sub>0.78</sub>Ni<sub>0.23</sub>Mn<sub>0.69</sub>O<sub>2</sub> Cathode Material for Na-Ion Batteries, Journal of the American Chemical Society, 139, pp. 4835-4845, (2017); Huang S., Cole J.M., BatteryBERT: A Pretrained Language Model for Battery Database Enhancement, J Chem Inf Model, 62, pp. 6365-6377, (2022); Mavracic J., Court C.J., Isazawa T., Elliott S.R., Cole J.M., ChemDataExtractor 2.0: Autopopulated Ontologies for Materials Science, Journal of Chemical Information and Modeling, 61, pp. 4280-4289, (2021); Ong S.P., Et al., Python Materials Genomics (pymatgen): A robust, open-source python library for materials analysis, Computational Materials Science, 68, pp. 314-319, (2013); Nomenclature of Inorganic Chemistry ‚Äì IUPAC Recommendations 2005, Chemistry International‚ÄìNewsmagazine for IUPAC, 27, pp. 25-26, (2005); In Advances in Information Retrieval, pp. 345-359; Tsoumakas G., Katakis I.M., Vlahavas I.P., Random k-Labelsets for Multilabel Classification, IEEE Trans. Knowl. Data Eng, 23, pp. 1079-1089, (2011); Gou Y., Zhang Y., Zhu J., Shu Y., figshare, (2024) | AC5: Y. Shu; School of Materials Science and Engineering, Sun Yat-sen University, Guangdong, China; email: shuyd@mail.sysu.edu.cn | AE5: Nature Research | AK5: 20524463 | AN5: 38605057.0 | AO5: English | AP5: Sci. Data | AQ5: Article | AR5: Final | AS5: All Open Access; Gold Open Access; Green Open Access | AT5: Scopus | AU5: 2-s2.0-85190269909 | AV5: q2 | AW5: Scopus | AX5: ? | AY5: =IF(AX5=TRUE,1,IF(AX5=FALSE,0,-1)) -> -1 | AZ5: TRUE | BA5: =IF(AZ5=TRUE,1,IF(AZ5=FALSE,0,-1)) -> 1 | BB5: ? | BC5: =IF(BB5=TRUE,1,IF(BB5=FALSE,0,-1)) -> -1 | BD5: 1 | BE5: 1 | BF5: 1 | BG5: 0 | BH5: =IF(BG5=1,"Yes",IF(BG5=-1,"Doubt","No")) -> No | BI5: =IF(BF5=1,"Yes","No") -> Yes | BJ5: 1 | BK5: Focused on Cathode materials. NER and RE as modules. Much more details about cathode materials than the pipeline for extracting anc creating such corpus.
A6: 133 | B6: Jian Z.; Liu S.; Yin H. | C6: Jian, Zhaorui (58175349700); Liu, Shenquan (59257789500); Yin, Huixin (58175877000) | D6: 58175349700; 59257789500; 58175877000 | E6: A Multi-granularity Contrastive Learning for Distantly Supervised Relation Extraction | F6: 2024.0 | G6: Lecture Notes in Computer Science (including subseries Lecture Notes in Artificial Intelligence and Lecture Notes in Bioinformatics) | H6: 14875 LNAI | K6: 352.0 | L6: 364.0 | M6: 12.0 | N6: 0.0 | O6: 10.1007/978-981-97-5663-6_30 | P6: https://www.scopus.com/inward/record.uri?eid=2-s2.0-85201218545&doi=10.1007%2f978-981-97-5663-6_30&partnerID=40&md5=a94b6f75958752616d7d6f9df49c03dd | Q6: School of Computer Science and Technology, Xinjiang University, Urumqi, 830046 , China | R6: Jian Z., School of Computer Science and Technology, Xinjiang University, Urumqi, 830046 , China; Liu S., School of Computer Science and Technology, Xinjiang University, Urumqi, 830046 , China; Yin H., School of Computer Science and Technology, Xinjiang University, Urumqi, 830046 , China | S6: Distant supervision, which automates the generation of annotated data, can alleviate the issue of data scarcity in model training. Previous works of distantly supervised relation extraction typically belonged to the bag-level approach, focusing on the context and background information of the entity pair within the instance bags while neglecting the complementarity and interaction between features of varying granularities. We introduce a Multi-Granularity Contrastive Learning for Distantly Supervised Relation Extraction (MGCL) to mitigate the adverse effects of noise in distant supervision. MGCL employs multi-granularity features to construct contrastive learning samples and adopts an asymmetrical contrastive classification strategy during the contrastive phase, aiding the model in understanding textual information from diverse perspectives, thereby obtaining richer and more multidimensional learning signals. In the contrasting process, MGCL also leverages the constraining connections between entities and relations to enrich the semantic background for rare relations. Experiments demonstrate that MGCL surpasses various mainstream baseline models in the relation extraction capability on the public dataset and surpasses the SOTA method in terms of AUC and P@M. This work not only advances the frontiers of distantly supervised relation extraction but also opens new avenues for exploring contrastive learning strategies in noisy environments. ¬© The Author(s), under exclusive license to Springer Nature Singapore Pte Ltd. 2024. | T6: Contrastive learning; Distantly supervised relation extraction; Multi-granularity feature interaction | U6: Classification (of information); Extraction; Learning systems; Background information; Context information; Contrastive learning; Data scarcity; Distantly supervised relation extraction; Feature interactions; Model training; Multi-granularity; Multi-granularity feature interaction; Relation extraction; Semantics | Z6: National Key Research and Development Program of China, NKRDPC, (2022ZD0115801); Major Science and Technology Projects in Xinjiang Uygur Autonomous Region, (2022A02012-1); National Natural Science Foundation of China, NSFC, (61966034) | AA6: This work was funded by the National Key R&D Program of China (No. 2022ZD0115801), the Major Science and Technology Projects in Xinjiang Uygur Autonomous Region (No. 2022A02012-1), and the National Natural Science Foundation of China (No. 61966034). | AB6: Zeng D., Liu K., Chen Y., Zhao J., Distant supervision for relation extraction via piecewise convolutional neural networks, Proceedings of the 2015 Conference on Empirical Methods in Natural Language Processing, pp. 1753-1762, (2015); Zhang J., Cao M., Distant supervision for relation extraction with hierarchical attention-based networks, Expert Syst. Appl., 220, (2023); Wu S., Fan K., Zhang Q., Improving distantly supervised relation extraction with neural noise converter and conditional optimal selector, Proceedings of the Thirty-Third AAAI Conference on Artificial Intelligence and Thirty-First Innovative Applications of Artificial Intelligence Conference and Ninth AAAI Symposium on Educational Advances in Artificial Intelligence, pp. 7273-7280, (2019); Li P., Zhang X., Jia W., Zhao H., Gan driven semi-distant supervision for relation extraction, Proceedings of the 2019 Conference of the North American Chapter of the Association for Computational Linguistics: Human Language Technologies, Volume 1 (Long and Short Papers),¬† Pp. 3026‚Äì3035, (2019); Ma R., Gui T., Li L., Zhang Q., Huang X.J., Zhou Y., Sent: Sentence-level distant relation extraction via negative training, Proceedings of the 59Th Annual Meeting of the Association for Computational Linguistics and the 11Th International Joint Conference on Natural Language Processing, 1, pp. 6201-6213, (2021); Li D., Zhang T., Hu N., Wang C., He X., HiCLRE: A hierarchical contrastive learning framework for distantly supervised relation extraction, Findings of the Association for Computational Linguistics: ACL, pp. 2567-2578, (2022); Devlin J., Chang M.W., Lee K., Toutanova K., BERT: Pre-training of deep bidirectional transformers for language understanding, Proceedings of the 2019 Conference of the North American Chapter of the Association for Computational Linguistics: Human Language Technologies, Volume 1 (Long and Short Papers), Pp. 4171‚Äì4186, (2019); Kipf T.N., Welling M., Semi-supervised classification with graph convolutional networks, International Conference on Learning Representations, (2016); Gao T., Yao X., Chen D., SimCSE: Simple contrastive learning of sentence embeddings, Proceedings of the 2021 Conference on Empirical Methods in Natural Language Processing, pp. 6894-6910, (2021); Wu X., Gao C., Zang L., Han J., Wang Z., Hu S., ESimCSE: Enhanced sample building method for contrastive learning of unsupervised sentence embedding, Proceedings of the 29Th International Conference on Computational Linguistics, pp. 3898-3907, (2022); Lin Y., Shen S., Liu Z., Luan H., Sun M., Neural relation extraction with selective attention over instances, Proceedings of the 54Th Annual Meeting of the Association for Computational Linguistics, 1, pp. 2124-2133, (2016); Liang T., Liu Y., Liu X., Zhang H., Sharma G., Guo M., Distantly-supervised long-tailed relation extraction using constraint graphs, IEEE Trans. Knowl. Data Eng., 35, 6852-6865, (2022); Pradhan S., Et al., Towards robust linguistic analysis using ontonotes, Proceedings of the Seventeenth Conference on Computational Natural Language Learning, pp. 143-152, (2013); Hadsell R., Chopra S., Lecun Y., Dimensionality reduction by learning an invariant mapping, 2006 IEEE Computer Society Conference on Computer Vision and Pattern Recognition (CVPR‚Äô06), Vol. 2, Pp. 1735‚Äì1742. IEEE, (2006); Oord A.V.D., Li Y., Vinyals O., Representation Learning with Contrastive Predictive Coding. Arxiv Preprint Arxiv, 1807, (2018); Riedel S., Yao L., McCallum A., Marlin B.M., Relation extraction with matrix factorization and universal schemas, Proceedings of the 2013 Conference of the North American Chapter of the Association for Computational Linguistics: Human Language Technologies, pp. 74-84, (2013); Alt C., Hubner M., Hennig L., Fine-tuning pre-trained transformer language models to distantly supervised relation extraction, Proceedings of the 57th¬†Annual Meeting of the Association for Computational Linguistics, pp. 1388-1398, (2019); Chen T., Shi H., Tang S., Chen Z., Wu F., Zhuang Y., CIL: Contrastive instance learning framework for distantly supervised relation extraction, Proceedings of the 59Th Annual Meeting of the Association for Computational Linguistics and the 11Th International Joint Conference on Natural Language Processing, 1, pp. 6191-6200, (2021); Zhang N., Deng S., Sun Z., Wang G., Chen X., Zhang W., Chen H., Longtail relation extraction via knowledge graph embeddings and graph convolution networks, Proceedings of the 2019 Conference of the North American Chapter of the Association for Computational Linguistics: Human Language Technologies, Volume 1 (Long and Short Papers), Pp. 3016‚Äì3025, (2019); Han X., Yu P., Liu Z., Sun M., Li P., Hierarchical relation extraction with coarse-to-fine grained attention, Proceedings of the 2018 Conference on Empirical Methods in Natural Language Processing, pp. 2236-2245, (2018); Cao Y., Kuang J., Gao M., Zhou A., Wen Y., Chua T.S., Learning relation prototype from unlabeled texts for long-tail relation extraction, IEEE Trans. Knowl. Data Eng., (2021); Soares L.B., Fitzgerald N., Ling J., Kwiatkowski T., Matching the blanks: Distributional similarity for relation learning, Proceedings of the 57Th Annual Meeting of the Association for Computational Linguistics, pp. 2895-2905, (2019); Vashishth S., Joshi R., Prayaga S.S., Bhattacharyya C., Talukdar P., Reside: Improving distantly-supervised neural relation extraction using side information, Proceedings of the 2018 Conference on Empirical Methods in Natural Language Processing, pp. 1257-1266, (2018); Christou D., Tsoumakas G., Improving distantly-supervised relation extraction through bert-based label and instance embeddings, IEEE Access, 9, pp. 62574-62582, (2021) | AC6: S. Liu; School of Computer Science and Technology, Xinjiang University, Urumqi, 830046 , China; email: liu@xju.edu.cn | AD6: Huang D.-S.; Zhang Q.; Zhang X. | AE6: Springer Science and Business Media Deutschland GmbH | AG6: 20th International Conference on Intelligent Computing, ICIC 2024 | AH6: 5 August 2024 through 8 August 2024 | AI6: Tianjin | AJ6: 316369.0 | AK6: 3029743 | AL6: 978-981975662-9 | AO6: English | AP6: Lect. Notes Comput. Sci. | AQ6: Conference paper | AR6: Final | AT6: Scopus | AU6: 2-s2.0-85201218545 | AV6: q2 | AW6: Scopus | AX6: ? | AY6: =IF(AX6=TRUE,1,IF(AX6=FALSE,0,-1)) -> -1 | AZ6: TRUE | BA6: =IF(AZ6=TRUE,1,IF(AZ6=FALSE,0,-1)) -> 1 | BB6: ? | BC6: =IF(BB6=TRUE,1,IF(BB6=FALSE,0,-1)) -> -1 | BD6: 1 | BE6: 1 | BF6: 1 | BG6: 1 | BH6: =IF(BG6=1,"Yes",IF(BG6=-1,"Doubt","No")) -> Yes | BI6: =IF(BF6=1,"Yes","No") -> Yes | BJ6: 1 | BK6: Multi-Granularity Contrastive Learning for Distantly Supervised Relation Extraction (MGCL) to enahnce the representations of rare data.
A7: 81 | B7: Zhang Z.; Yang Y.; Chen B. | C7: Zhang, Zirui (58162269500); Yang, Yiyu (58251063100); Chen, Benhui (35179094700) | D7: 58162269500; 58251063100; 35179094700 | E7: A prompt tuning method based on relation graphs for few-shot relation extraction | F7: 2025.0 | G7: Neural Networks | H7: 185 | J7: 107214 | N7: 0.0 | O7: 10.1016/j.neunet.2025.107214 | P7: https://www.scopus.com/inward/record.uri?eid=2-s2.0-85216698989&doi=10.1016%2fj.neunet.2025.107214&partnerID=40&md5=928604dc0b7d0511bed4bc566cf318d8 | Q7: Nanjing University of Aeronautics and Astronautics, Jiangsu, Nanjing, 210016, China; Dali University, Yunnan, Dali, 671000, China; Lijiang Normal College, Yunnan, Lijiang, 674100, China | R7: Zhang Z., Nanjing University of Aeronautics and Astronautics, Jiangsu, Nanjing, 210016, China; Yang Y., Dali University, Yunnan, Dali, 671000, China; Chen B., Dali University, Yunnan, Dali, 671000, China, Lijiang Normal College, Yunnan, Lijiang, 674100, China | S7: Prompt-tuning has recently proven effective in addressing few-shot tasks. However, task resources remain severely limited in the specific domain of few-shot relation extraction. Despite its successes, prompt-tuning faces challenges distinguishing between similar relations, resulting in occasional prediction errors. Therefore, it is critical to extract maximum information from these scarce resources. This paper introduces the integration of global relation graphs and local relation subgraphs into the prompt-tuning framework to tackle this issue and fully exploit the available resources for differentiating between various relations. A global relation graph is initially constructed to enhance feature representations of samples across different relations based on label consistency. Subsequently, this global relation graph is partitioned to create local relation subgraphs for each relation type, optimizing the feature representations of samples within the same relation. This dual approach effectively utilizes the limited supervised information and improves tuning efficiency. Additionally, recognizing the substantial semantic knowledge embedded in relation labels, this study integrates such knowledge into the prompt-tuning process. Extensive experiments conducted on four low-resource datasets validate the efficacy of the proposed method, demonstrating significant performance improvements. Notably, the model also exhibits robust performance in discerning similar relations. ¬© 2025 Elsevier Ltd | T7: Few-shot; Knowledge graph; Prompt tuning; Relation extraction; Relation graph | U7: Feature representation; Few-shot; Knowledge graphs; Prediction errors; Prompt tuning; Relation extraction; Relation graph; Scarce resources; Subgraphs; Tuning method; aged; article; controlled study; human; pharmacokinetics; prediction error; Knowledge graph | AB7: Alt C., Gabryszak A., Hennig L., TACRED revisited: A thorough evaluation of the TACRED relation extraction task, (2020); Ben-David E., Oved N., Reichart R., Pada: A prompt-based autoregressive approach for adaptation to unseen domains, (2021); Brown T., Mann B., Ryder N., Subbiah M., Kaplan J.D., Dhariwal P., Et al., Language models are few-shot learners, Advances in Neural Information Processing Systems, 33, pp. 1877-1901, (2020); Chen X., Xie X., Zhang N., Yan J., Deng S., Tan C., Et al., AdaPrompt: Adaptive prompt-based finetuning for relation extraction, (2021); Chen X., Zhang N., Xie X., Deng S., Yao Y., Tan C., Et al., (2022); Devlin J., Chang M.W., Lee K., Toutanova K., Bert: Pre-training of deep bidirectional transformers for language understanding, (2018); Feng J., Wei Q., Cui J., Prototypical networks relation classification model based on entity convolution, Computer Speech and Language, 77, (2023); Gao T., Fisch A., Chen D., Making pre-trained language models better few-shot learners, (2020); Gao T., Han X., Liu Z., Sun M., 33, (2019); Han X., Zhao W., Ding N., Liu Z., Sun M., Ptr: Prompt tuning with rules for text classification, AI Open, 3, pp. 182-192, (2022); Han X., Zhu H., Yu P., Wang Z., Yao Y., Liu Z., Et al., FewRel: A large-scale supervised few-shot relation classification dataset with state-of-the-art evaluation, (2018); He K., Huang Y., Mao R., Gong T., Li C., Cambria E., Virtual prompt pre-training for prototype-based few-shot relation extraction, Expert Systems with Applications, 213, (2023); He H., Niu H., Feng J., Wang Q., Wei Q., A prototype network enhanced relation semantic representation for few-shot relation extraction, Human-Centric Intelligent Systems, 3, 1, pp. 1-12, (2023); Hendrickx I., Kim S.N., Kozareva Z., Nakov P., Seaghdha D.O., Pado S., Et al., Semeval-2010 task 8: Multi-way classification of semantic relations between pairs of nominals, (2019); Joshi M., Chen D., Liu Y., Weld D.S., Zettlemoyer L., Levy O., Spanbert: Improving pre-training by representing and predicting spans, Transactions of the Association for Computational Linguistics, 8, pp. 64-77, (2020); Lester B., Al-Rfou R., Constant N., The power of scale for parameter-efficient prompt tuning, (2021); Lewis M., Liu Y., Goyal N., Ghazvininejad M., Mohamed A., Levy O., Et al., Bart: Denoising sequence-to-sequence pre-training for natural language generation, translation, and comprehension, (2019); Li X., Liu C., Yu J., Xu T., Zhao M., Liu H., Et al., Prototypical attention network for few-shot relation classification with entity-aware embedding module, Applied Intelligence: The International Journal of Artificial Intelligence, Neural Networks, and Complex Problem-Solving Technologies, 53, 9, pp. 10978-10994, (2023); Liu Y., Ott M., Goyal N., Du J., Joshi M., Chen D., Et al., Roberta: A robustly optimized bert pretraining approach, (2019); Liu P., Yuan W., Fu J., Jiang Z., Hayashi H., Neubig G., Pre-train, prompt, and predict: A systematic survey of prompting methods in natural language processing, ACM Computing Surveys, 55, 9, pp. 1-35, (2023); Lu Y., Bartolo M., Moore A., Riedel S., Stenetorp P., Fantastically ordered prompts and where to find them: Overcoming few-shot prompt order sensitivity, (2021); Paolini G., Athiwaratkun B., Krone J., Ma J., Achille A., Anubhai R., Et al., Structured prediction as translation between augmented natural languages, (2021); Peters M.E., Neumann M., Logan R.L., Schwartz R., Joshi V., Singh S., Et al., Knowledge enhanced contextual word representations, (2019); Raffel C., Shazeer N., Roberts A., Lee K., Narang S., Matena M., Et al., Exploring the limits of transfer learning with a unified text-to-text transformer, Journal of Machine Learning Research, 21, 1, pp. 5485-5551, (2020); Reynolds L., (2021); Scao T.L., Rush A.M., How many data points is a prompt worth?, (2021); Schick T., Schutze H., Exploiting cloze questions for few shot text classification and natural language inference, (2020); Schick T., Schutze H., It's not just size that matters: Small language models are also few-shot learners, (2020); Snell J., Swersky K., Zemel R., Prototypical networks for few-shot learning, Advances in Neural Information Processing Systems, 30, (2017); Soares L.B., Fitzgerald N., Ling J., Kwiatkowski T., Matching the blanks: distributional similarity for relation learning, (2019); Stoica G., Platanios E.A., 35, (2021); Sui D., Zeng X., Chen Y., Liu K., Zhao J., Joint entity and relation extraction with set prediction networks, IEEE Transactions on Neural Networks and Learning Systems, (2023); Xu X., Chen X., Zhang N., Xie X., Chen X., Chen H., Towards realistic low-resource relation extraction: A benchmark with empirical baseline study, (2022); Xue F., Sun A., Zhang H., Chng E., 35, (2021); Yamada I., Asai A., Shindo H., Takeda H., Matsumoto Y., Luke: deep contextualized entity representations with entity-aware self-attention, (2020); Ye H., Zhang N., Deng S., Chen X., Chen H., Xiong F., Et al., (2022); Zhang Y., Zhong V., Chen D., Angeli G., Manning C., (2017); Zhenzhen L., Zhang Y., Nie J.Y., Li D., (2022); Zhou W., Chen M., An improved baseline for sentence-level relation extraction, (2021) | AC7: Z. Zhang; Nanjing University of Aeronautics and Astronautics, Nanjing, Jiangsu, 210016, China; email: zhangzirui@nuaa.edu.cn | AE7: Elsevier Ltd | AK7: 8936080 | AM7: NNETE | AO7: English | AP7: Neural Netw. | AQ7: Article | AR7: Final | AT7: Scopus | AU7: 2-s2.0-85216698989 | AV7: q1 | AW7: Scopus | AX7: ? | AY7: =IF(AX7=TRUE,1,IF(AX7=FALSE,0,-1)) -> -1 | AZ7: TRUE | BA7: =IF(AZ7=TRUE,1,IF(AZ7=FALSE,0,-1)) -> 1 | BB7: ? | BC7: =IF(BB7=TRUE,1,IF(BB7=FALSE,0,-1)) -> -1 | BD7: 1 | BE7: 1 | BF7: 1 | BG7: 1 | BH7: =IF(BG7=1,"Yes",IF(BG7=-1,"Doubt","No")) -> Yes | BI7: =IF(BF7=1,"Yes","No") -> Yes | BJ7: 1 | BK7: Promptuning models by global and locas KGs (DSRE) through prompts with zero shot setting.
A8: 5 | B8: Xu H. | C8: Xu, Haoshuai (57224534746) | D8: 57224534746 | E8: A Prompt-tuning Method For Low-Resource Relation Extraction Based On Enhanced-Prototype | F8: 2023.0 | G8: 2023 7th International Conference on Electrical, Mechanical and Computer Engineering, ICEMCE 2023 | K8: 798.0 | L8: 801.0 | M8: 3.0 | N8: 0.0 | O8: 10.1109/ICEMCE60359.2023.10490490 | P8: https://www.scopus.com/inward/record.uri?eid=2-s2.0-85191415434&doi=10.1109%2fICEMCE60359.2023.10490490&partnerID=40&md5=f6bd164126426bd0e5dec2ac0daaae51 | Q8: School of Information Management, Wuhan University, Wuhan, China | R8: Xu H., School of Information Management, Wuhan University, Wuhan, China | S8: Prompt-tuning has been successful in low resource relation extraction. Since there are many relation labels in relation extraction task, it is a challenge to build label verbalizer, which mapping answer word to label space. To address this problem, we propose a prototype construction strategy based on relation semantic enhancement and Prototypical Network, which use attention mechanisms to calculate weighted averages of answer word embedding in support set. We also propose an entity type-enhanced answer word optimization approach to refine the answer word embedding based entity type information in relation context. We conduct experiments on the TACRED and TACRED-Revisit datasets. The experimental results demonstrate that our methods in enhance the accuracy of prototype construction and answer word embeddings. ¬© 2023 IEEE. | T8: component; low resource; prompt-tuning; relation extraction | U8: Extraction; Semantics; Component; Construction strategies; Embeddings; Entity-types; Label space; Low resource; Prompt-tuning; Relation extraction; Relation semantics; Tuning method; Embeddings | AB8: Wang H., Qin K., Lu G., Luo G., Liu G., Direction-sensitive relation extraction using bi-sdp attention model, Knowledge-Based Systems, 198, (2020); Xu X., Chen X., Zhang N., Xie X., Chen X., Chen H., Towards Realistic Low-resource Relation Extraction: A Benchmark with Empirical Baseline Study, Findings of the Association for Computational Linguistics: EMNLP 2022, pp. 413-427, (2022); Liu P., Yuan W., Fu J., Jiang Z., Hayashi H., Neubig G., Pre-train, prompt, and predict: A systematic survey of prompting methods in natural language processing, ACM Computing Surveys, 55, 9, pp. 1-35, (2023); Gao T., Fisch A., Chen D., Making Pre-trained Language Models Better Few-shot Learners, Proceedings of the 59th Annual Meeting of the Association for Computational Linguistics and the 11th International Joint Conference on Natural Language Processing( volume 1: Long Papers), pp. 3816-3830, (2021); Shin T., Razeghi Y., Iv Logan R.L., Wallace E., Singh S., AutoPrompt: Eliciting Knowledge from Language Models with Automatically Generated Prompts, Proceedings of the 2020 Conference on Empirical Methods in Natural Language Processing (EMNLP), pp. 4222-4235, (2020); Liu X., Et al., P-tuning: Prompt tuning can be comparable to fine-tuning across scales and tasks, Proceedings of the 60th Annual Meeting of the Association for Computational Linguistics(volume 2: Short Papers), pp. 61-68, (2022); Chen X., Et al., KnowPrompt: Knowledge-aware Prompt-tuning with Synergistic Optimization for Relation Extraction, The Proceedings of the ACM Web Conference 2022, (2022); Arora S., Liang Y., Ma T., A Simple but Tough-to-Beat Baseline for Sentence Embeddings, International Conference on Learning Representations, (2016); Li W., Qian T., Chen X., Tang K., Zhan S., Zhan T., Exploit a Multi-head Reference Graph for Semi-supervised Relation Extraction, 2021 International Joint Conference on Neural Networks (IJCNN), pp. 1-7, (2021); Ye H., Et al., Ontology-enhanced Prompt-tuning for Few-shot Learning, Proceedings of the ACM Web Conference 2022, pp. 778-787, (2022) | AC8: H. Xu; School of Information Management, Wuhan University, Wuhan, China; email: hsh.xu@foxmail.com | AE8: Institute of Electrical and Electronics Engineers Inc. | AF8: IEEE | AG8: 7th International Conference on Electrical, Mechanical and Computer Engineering, ICEMCE 2023 | AH8: 20 October 2023 through 22 October 2023 | AI8: Hybrid, Xi'an | AJ8: 198913.0 | AL8: 979-835038287-7 | AO8: English | AP8: Int. Conf. Electr., Mech. Comput. Eng., ICEMCE | AQ8: Conference paper | AR8: Final | AT8: Scopus | AU8: 2-s2.0-85191415434 | AV8: q1 | AW8: Scopus | AX8: TRUE | AY8: =IF(AX8=TRUE,1,IF(AX8=FALSE,0,-1)) -> 1 | AZ8: TRUE | BA8: =IF(AZ8=TRUE,1,IF(AZ8=FALSE,0,-1)) -> 1 | BB8: TRUE | BC8: =IF(BB8=TRUE,1,IF(BB8=FALSE,0,-1)) -> 1 | BD8: 1 | BE8: 1 | BF8: 1 | BG8: -1 | BH8: =IF(BG8=1,"Yes",IF(BG8=-1,"Doubt","No")) -> Doubt | BI8: =IF(BF8=1,"Yes","No") -> Yes | BJ8: 1 | BK8: It speaks more about semantic similarity. In this case, it adds prototyping with prompt learning and contrastive learning with entity information.
A9: 13 | B9: Wang H.; Mao X.-L.; Huang H. | C9: Wang, Hao (59648940800); Mao, Xian-Ling (56949703000); Huang, Heyan (7405614195) | D9: 59648940800; 56949703000; 7405614195 | E9: A Semi-supervised Transfer Learning Framework for Low Resource Entity and Relation Extraction in Scientific Domain | F9: 2022.0 | G9: CEUR Workshop Proceedings | H9: 3210 | K9: 41.0 | L9: 47.0 | M9: 6.0 | N9: 1.0 | P9: https://www.scopus.com/inward/record.uri?eid=2-s2.0-85138353661&partnerID=40&md5=b57203f9b0ae739e9ab77ae6980ee484 | Q9: Beijing Institute of Technology, No.5, Zhongguancun South Street, Beijing, 100081, China | R9: Wang H., Beijing Institute of Technology, No.5, Zhongguancun South Street, Beijing, 100081, China; Mao X.-L., Beijing Institute of Technology, No.5, Zhongguancun South Street, Beijing, 100081, China; Huang H., Beijing Institute of Technology, No.5, Zhongguancun South Street, Beijing, 100081, China | S9: With the development of scientific communities, the amount of papers increases quickly. It's important to convert the unstructured scientific papers into structured knowledge base, which relies on Information Extraction (IE) to extract entities and their relationships. Most existing IE methods require abundant annotated data, which is time-consuming and expensive to obtain, especially in scientific domain because it requires annotators with domain knowledge. Recently, several works have been proposed to solve the problem by semi-supervised learning. However, these methods require the input sentence to contain only two entities and simply classify the relationship between these two entities. Obviously, it is far from the realistic application scenarios that both entities and relations need to be extracted from raw text. In this paper, we propose a Semi-supervised Transfer Learning (STL) framework to tackle joint entity and relation extraction problem in a low resource situation. Specifically, STL adopts two main strategies: a rebalancing strategy for alleviating the bias to the majority class during semi-supervised learning, and a transfer learning strategy for transferring knowledge from domains with relatively rich annotation to domains that lack annotated data. Experiment results on two public scientific IE datasets show the effectiveness of the proposed method. ¬© 2022 Copyright for this paper by its author. | T9: Information Extraction; Semi-supervised Learning; Transfer Learning | U9: Data mining; Information retrieval; Learning algorithms; Learning systems; Transfer learning; Entity extractions; Information extraction; Learning frameworks; Relation extraction; Scientific community; Scientific papers; Semi-supervised; Semi-supervised learning; Structured knowledge; Transfer learning; Domain Knowledge | AB9: Bekoulis Giannis, Deleu Johannes, Demeester Thomas, Develder Chris, Adversarial training for multi-context joint entity and relation extraction, InProceedings of the 2018 Conference on Empirical Methods in Natural LanguageProcessing, pp. 2830-2836, (2018); Beltagy Iz, Lo Kyle, Cohan Arman, SciBERT: A Pretrained LanguageModel for Scientific Text, Proceedings of the 2019 Conference on EmpiricalMethods in Natural Language Processing and the 9th International Joint Conferenceon Natural Language Processing (EMNLP-IJCNLP), pp. 3615-3620, (2019); Di Shimin, Shen Yanyan, Chen Lei, Relation extraction via domain-aware transfer learning, Proceedings of the 25th ACM SIGKDD internationalconference on knowledge discovery & Data Mining, pp. 1348-1357, (2019); Eberts Markus, Ulges Adrian, Span-based joint entity and relation extraction with transformer pre-training, (2019); Gurulingappa Harsha, Rajput Abdul Mateen, Roberts Angus, Fluck Juliane, Hofmann-Apitius Mar-tin, Toldo Luca, Development of a benchmark corpusto support the automatic extraction of drug-related adverse effects from medicalcase reports, Journal of biomedical informatics, 45, 5, pp. 885-892, (2012); Hafiane Walid, Legrand Joel, Toussaint Yannick, Coulet Adrien, Experiments on transfer learning architectures for biomedical relation extraction, (2020); Hu Xuming, Zhang Chenwei, Ma Fukun, Liu Chenyao, Wen Lijie, Yu Philip S, Semi-supervised Relation Extraction via Incremental Meta Self-Training, InFindings of the Association for Computational Linguistics: EMNLP, 2021, pp. 487-496, (2021); Hu Xuming, Zhang Chenwei, Yang Yawen, Li Xiaohe, Lin Li, Wen Lijie, Philip andS Yu, Gradient Imitation Reinforcement Learning for Low ResourceRelation Extraction, Proceedings of the 2021 Conference on Empirical Methodsin Natural Language Processing, pp. 2737-2746, (2021); Jawahar Ganesh, Sagot Benoit, Seddah Djame, What does BERTlearn about the structure of language?, ACL 2019-57th Annual Meeting of theAssociation for Computational Linguistics, (2019); Lee Jinhyuk, Yoon Wonjin, Kim Sungdong, Kim Donghyeon, Kim Sunkyu, So Chan Ho, Kang Jaewoo, BioBERT: a pre-trained biomedical lan-guage representation model for biomedical text mining, Bioinformatics, 36, 4, pp. 1234-1240, (2020); Legrand Joel, Toussaint Yannick, Raissi Chedy, Coulet Adrien, Syntax-based transfer learning for the task of biomedical relation extraction, Journal ofBiomedical Semantics, 12, 1, pp. 1-11, (2021); Lin Hongtao, Yan Jun, Qu Meng, Ren Xiang, Learning dual retrievalmodule for semi-supervised relation extraction, The World Wide Web Confer-ence, pp. 1073-1083, (2019); Luan Yi, He Luheng, Ostendorf Mari, Hajishirzi Hannaneh, MultiTaskIdentification of Entities, Relations, and Coreference for Scientific KnowledgeGraph Construction, Proceedings of the 2018 Conference on Empirical Methodsin Natural Language Processing, pp. 3219-3232, (2018); Ruder Sebastian, Peters Matthew E, Swayamdipta Swabha, Wolf Thomas, Transfer learning in natural language processing, Proceedings of the2019 conference of the North American chapter of the association for computationallinguistics: Tutorials, pp. 15-18, (2019); Scudder Henry, Probability of error of some adaptive pattern-recognitionmachines, IEEE Transactions on Information Theory, 11, 3, pp. 363-371, (1965); Taille Bruno, Guigue Vincent, Scoutheeten Geoffrey, Gallinari Patrick, Let's Stop Incorrect Comparisons in End-to-end Relation Extraction! arXivpreprint, (2020); Vaswani Ashish, Shazeer Noam, Parmar Niki, Uszkoreit Jakob, Jones Llion, Gomez Aidan N, Kaiser Lukasz, Polosukhin Illia, Attention is allyou need, Advances in neural information processing systems, 30, (2017); Wei Chen, Sohn Kihyuk, Mellina Clayton, Yuille Alan, Yang Fan, Crest:A class-rebalancing self-training framework for imbalanced semi-supervisedlearning, Proceedings of the IEEE/CVF Conference on Computer Vision andPattern Recognition, pp. 10857-10866, (2021); Zhou Wenxuan, Lin Hongtao, Lin Bill Yuchen, Wang Ziqi, Du Junyi, LeonardoNeves, Ren Xiang, Nero: A neural rule grounding framework forlabel-efficient relation extraction, Proceedings of The Web Conference 2020, pp. 2166-2176, (2020) | AD9: Zhang C.; Nanjing University of Science and Technology, No. 200, Xiaolinvgwei, Nanjing; Mayr P.; GESIS - Leibniz Institute for the Social Sciences, Knowledge Technologies for the Social Sciences, Unter Sachsenhausen 6-8, Cologne; Lu W.; Zhang Y.; University of Technology Sydney, Australian Artificial Intelligence Institute, 15 Broadway, Ultimo, NSW | AE9: CEUR-WS | AG9: 3rd Workshop on Extraction and Evaluation of Knowledge Entities from Scientific Documents, EEKE 2022 | AH9: 23 June 2022 through 24 June 2022 | AI9: Virtual, Online | AJ9: 182600.0 | AK9: 16130073 | AO9: English | AP9: CEUR Workshop Proc. | AQ9: Conference paper | AR9: Final | AT9: Scopus | AU9: 2-s2.0-85138353661 | AV9: q1 | AW9: Scopus | AX9: TRUE | AY9: =IF(AX9=TRUE,1,IF(AX9=FALSE,0,-1)) -> 1 | AZ9: TRUE | BA9: =IF(AZ9=TRUE,1,IF(AZ9=FALSE,0,-1)) -> 1 | BB9: TRUE | BC9: =IF(BB9=TRUE,1,IF(BB9=FALSE,0,-1)) -> 1 | BD9: 1 | BE9: 1 | BF9: 1 | BG9: 0 | BH9: =IF(BG9=1,"Yes",IF(BG9=-1,"Doubt","No")) -> No | BI9: =IF(BF9=1,"Yes","No") -> Yes | BJ9: 1 | BK9: It speaks about IE within two taks: NER and RE. It seems to be speaking about triplet extraction.
A10: 10 | B10: Han P.; Liang G.; Wang Y. | C10: Han, Peisheng (57072499600); Liang, Geng (59552118400); Wang, Yongfei (55762258300) | D10: 57072499600; 59552118400; 55762258300 | E10: A Zero-Shot Framework for Low-Resource Relation Extraction via Distant Supervision and Large Language Models | F10: 2025.0 | G10: Electronics (Switzerland) | H10: 14 | I10: 3.0 | J10: 593 | N10: 0.0 | O10: 10.3390/electronics14030593 | P10: https://www.scopus.com/inward/record.uri?eid=2-s2.0-85217573729&doi=10.3390%2felectronics14030593&partnerID=40&md5=328e326276c11f573e1073d524714b8f | Q10: Institute of Cryptographic Engineering, PLA Information Engineering University, Zhengzhou, 450001, China | R10: Han P., Institute of Cryptographic Engineering, PLA Information Engineering University, Zhengzhou, 450001, China; Liang G., Institute of Cryptographic Engineering, PLA Information Engineering University, Zhengzhou, 450001, China; Wang Y., Institute of Cryptographic Engineering, PLA Information Engineering University, Zhengzhou, 450001, China | S10: While Large Language Models (LLMs) have significantly advanced various benchmarks in Natural Language Processing (NLP), the challenge of low-resource tasks persists, primarily due to the scarcity of data and difficulties in annotation. This study introduces LoRE, a framework designed for zero-shot relation extraction in low-resource settings, which blends distant supervision with the powerful capabilities of LLMs. LoRE addresses the challenges of data sparsity and noise inherent in traditional distant supervision methods, enabling high-quality relation extraction without requiring extensive labeled data. By leveraging LLMs for zero-shot open information extraction and incorporating heuristic entity and relation alignment with semantic disambiguation, LoRE enhances the accuracy and relevance of the extracted data. Low-resource tasks refer to scenarios where labeled data are extremely limited, making traditional supervised learning approaches impractical. This study aims to develop a robust framework that not only tackles these challenges but also demonstrates the theoretical and practical implications of zero-shot relation extraction. The Chinese Person Relationship Extraction (CPRE) dataset, developed under this framework, demonstrates LoRE‚Äôs proficiency in extracting person-related triples. The CPRE dataset consists of 1000 word pairs, capturing diverse semantic relationships. Extensive experiments on the CPRE, IPRE, and DuIE datasets show significant improvements in dataset quality and a reduction in manual annotation efforts. These findings highlight the potential of LoRE to advance both the theoretical understanding and practical applications of relation extraction in low-resource settings. Notably, the performance of LoRE on the manually annotated DuIE dataset attests to the quality of the CPRE dataset, rivaling that of manually curated datasets, and highlights LoRE‚Äôs potential for reducing the complexities and costs associated with dataset construction for zero-shot and low-resource tasks. ¬© 2025 by the authors. | T10: distant supervision; knowledge graphs; large language models; low-resource relation extraction; zero-shot learning | Z10: National Natural Science Foundation of China, NSFC, (61572517); National Natural Science Foundation of China, NSFC | AA10: This work was supported in part by the National Natural Science Foundation of China (61572517). | AB10: Zhou W., Zhang S., Naumann T., Chen M., Poon H., Continual Contrastive Finetuning Improves Low-Resource Relation Extraction, Proceedings of the 61st Annual Meeting of the Association for Computational Linguistics (Volume 1: Long Papers), pp. 13249-13263; Gururaja S., Dutt R., Liao T., Rose C., Linguistic representations for fewer-shot relation extraction across domains, Proceedings of the 61st Annual Meeting of the Association for Computational Linguistics (Volume 1: Long Papers), pp. 7502-7514; Xu B., Wang Q., Lyu Y., Dai D., Zhang Y., Mao Z., S2ynRE: Two-stage Self-training with Synthetic data for Low-resource Relation Extraction, Proceedings of the 61st Annual Meeting of the Association for Computational Linguistics (Volume 1: Long Papers), pp. 8186-8207; Bonifacio L., Abonizio H., Fadaee M., Nogueira R., Inpars: Data augmentation for information retrieval using large language models, arXiv, (2022); Gholami S., Omar M., Does Synthetic Data Make Large Language Models More Efficient?, arXiv, (2023); Mintz M., Bills S., Snow R., Jurafsky D., Distant Supervision for Relation Extraction without Labeled Data, Proceedings of the Joint Conference of the 47th Annual Meeting of the ACL and the 4th International Joint Conference on Natural Language Processing of the AFNLP: Volume 2‚ÄîVolume 2, ACL ‚Äô09, pp. 1003-1011; Schick T., Schutze H., True Few-Shot Learning with Prompts‚ÄîA Real-World Perspective, Trans. Assoc. Comput. Linguist, 10, pp. 716-731, (2022); Xiao Y., Jin Y., Cheng R., Hao K., Hybrid attention-based transformer block model for distant supervision relation extraction, Neurocomputing, 470, pp. 29-39, (2022); Ben Abacha A., Zweigenbaum P., Automatic extraction of semantic relations between medical entities: A rule based approach, J. Biomed. Semant, 2, pp. 1-11, (2011); Cui M., Li L., Wang Z., You M., A Survey on Relation Extraction, Proceedings of the Knowledge Graph and Semantic Computing. Language, Knowledge, and Intelligence, pp. 50-58, (2017); Zhou K., Qiao Q., Li Y., Li Q., Improving Distantly Supervised Relation Extraction by Natural Language Inference, Proc. AAAI Conf. Artif. Intell, 37, pp. 14047-14055, (2023); Chen J., Guo Z., Yang J., Distant Supervision for Relation Extraction via Noise Filtering, Proceedings of the 2021 13th International Conference on Machine Learning and Computing, ICMLC ‚Äô21, pp. 361-367; Kumar V., Ntoutsi E., Rajawat P.S., Medda G., Recupero D.R., Unlocking LLMs: Addressing Scarce Data and Bias Challenges in Mental Health, arXiv, (2024); Hiller M., Ma R., Harandi M., Drummond T., Rethinking generalization in few-shot classification, Adv. Neural Inf. Process. Syst, 35, pp. 3582-3595, (2022); Wadhwa S., Amir S., Wallace B., Revisiting Relation Extraction in the era of Large Language Models, Proceedings of the 61st Annual Meeting of the Association for Computational Linguistics (Volume 1: Long Papers), pp. 15566-15589; Xu X., Zhu Y., Wang X., Zhang N., How to Unleash the Power of Large Language Models for Few-shot Relation Extraction?, Proceedings of the Fourth Workshop on Simple and Efficient Natural Language Processing (SustaiNLP), pp. 190-200; Li B., Fang G., Yang Y., Wang Q., Ye W., Zhao W., Zhang S., Evaluating ChatGPT‚Äôs Information Extraction Capabilities: An Assessment of Performance, Explainability, Calibration, and Faithfulness, arXiv, (2023); Liu H., GitHub Repository, (2018); Li J., Cheng X., Zhao W.X., Nie J.Y., Wen J.R., Halueval: A large-scale hallucination evaluation benchmark for large language models, arXiv, (2023); Huang C., Li X., Jiang Y., Lv W., Xu M., Feature Extension for Chinese Short Text Based on Tongyici Cilin, Computer and Information Science, pp. 167-180, (2023); Li S., He W., Shi Y., Jiang W., Liang H., Jiang Y., Zhang Y., Lyu Y., Zhu Y., DuIE: A Large-Scale Chinese Dataset for Information Extraction, Natural Language Processing and Chinese Computing: 8th CCF International Conference, NLPCC 2019, Dunhuang, China, October 9‚Äì14, 2019, Proceedings, Part II 8, pp. 791-800, (2019); Wang H., He Z., Ma J., Chen W., Zhang M., IPRE: A Dataset for Inter-Personal Relationship Extraction, Natural Language Processing and Chinese Computing: 8th CCF International Conference, NLPCC 2019, Dunhuang, China, October 9‚Äì14, 2019, Proceedings, Part II 8, pp. 103-115, (2019); Brody S., Wu S., Benton A., Towards realistic few-shot relation extraction, Proceedings of the 2021 Conference on Empirical Methods in Natural Language Processing, pp. 5338-5345; Devlin J., Chang M.W., Lee K., Toutanova K., BERT: Pre-training of Deep Bidirectional Transformers for Language Understanding, Proceedings of the 2019 Conference of the North American Chapter of the Association for Computational Linguistics: Human Language Technologies, Volume 1 (Long and Short Papers), pp. 4171-4186; Huguet Cabot P.L., Navigli R., REBEL: Relation Extraction By End-to-end Language generation, Proceedings of the Findings of the Association for Computational Linguistics: EMNLP 2021, pp. 2370-2381; Radford A., Wu J., Child R., Luan D., Amodei D., Sutskever I., Language models are unsupervised multitask learners, OpenAI Blog, 1, (2019); Shang Y.M., Huang H., Mao X., OneRel: Joint Entity and Relation Extraction with One Module in One Step, Proceedings of the AAAI Conference on Artificial Intelligence, 36, pp. 11285-11293; Wei Z., Su J., Wang Y., Tian Y., Chang Y., A Novel Cascade Binary Tagging Framework for Relational Triple Extraction, Proceedings of the 58th Annual Meeting of the Association for Computational Linguistics, pp. 1476-1488 | AC10: P. Han; Institute of Cryptographic Engineering, PLA Information Engineering University, Zhengzhou, 450001, China; email: hps9743003@163.com | AE10: Multidisciplinary Digital Publishing Institute (MDPI) | AK10: 20799292 | AO10: English | AP10: Electronics (Switzerland) | AQ10: Article | AR10: Final | AS10: All Open Access; Gold Open Access | AT10: Scopus | AU10: 2-s2.0-85217573729 | AV10: q1 | AW10: Scopus | AX10: ? | AY10: =IF(AX10=TRUE,1,IF(AX10=FALSE,0,-1)) -> -1 | AZ10: TRUE | BA10: =IF(AZ10=TRUE,1,IF(AZ10=FALSE,0,-1)) -> 1 | BB10: TRUE | BC10: =IF(BB10=TRUE,1,IF(BB10=FALSE,0,-1)) -> 1 | BD10: 1 | BE10: 1 | BF10: 1 | BG10: 1 | BH10: =IF(BG10=1,"Yes",IF(BG10=-1,"Doubt","No")) -> Yes | BI10: =IF(BF10=1,"Yes","No") -> Yes | BJ10: 1 | BK10: Semantic similarity. It makes RE for low resources with LLMs and DSRE to improve representations of noisy and incorrect data.
A11: 55 | B11: Shi Y.; Jiang G.; Qiu T.; Yang D. | C11: Shi, Yuchen (57666097800); Jiang, Guochao (59008975200); Qiu, Tian (59339310600); Yang, Deqing (56138582400) | D11: 57666097800; 59008975200; 59339310600; 56138582400 | E11: AgentRE: An Agent-Based Framework for Navigating Complex Information Landscapes in Relation Extraction | F11: 2024.0 | G11: International Conference on Information and Knowledge Management, Proceedings | K11: 2045.0 | L11: 2055.0 | M11: 10.0 | N11: 1.0 | O11: 10.1145/3627673.3679791 | P11: https://www.scopus.com/inward/record.uri?eid=2-s2.0-85210024610&doi=10.1145%2f3627673.3679791&partnerID=40&md5=0eadba098cac7e3acf4b36a354d804ab | Q11: School of Data Science, Fudan University, Shanghai, China | R11: Shi Y., School of Data Science, Fudan University, Shanghai, China; Jiang G., School of Data Science, Fudan University, Shanghai, China; Qiu T., School of Data Science, Fudan University, Shanghai, China; Yang D., School of Data Science, Fudan University, Shanghai, China | S11: The relation extraction (RE) in complex scenarios faces challenges such as diverse relation types and ambiguous relations between entities within a single sentence, leading to the poor performance of pure "text-in, text-out"language models (LMs). To address these challenges, in this paper, we propose an agent-based RE framework, namely "AgentRE", which fully leverages the potential of large language models (LLMs) including memory, retrieval and reflection, to achieve RE in complex scenarios. Specifically, three major modules are built in AgentRE serving as the tools to help the agent acquire and process various useful information, thereby obtaining improved RE performance. Our extensive experimental results upon two datasets in English and Chinese demonstrate our AgentRE's superior performance, especially in low-resource scenarios. Additionally, the trajectories generated by AgentRE can be refined to construct a high-quality training dataset incorporating different reasoning methods, which can be used to fine-tune smaller models. ¬© 2024 ACM. | T11: agent; large language model; memory; relation extraction; retrieval | U11: Autonomous agents; Agent based; Agent-based framework; Complex information; Language model; Large language model; Memory retrieval; Performance; Poor performance; Relation extraction; Retrieval; Modeling languages | Z11: Major Research Plan, (92270121, 62102095); Major Research Plan; Science and Technology Innovation Plan Of Shanghai Science and Technology Commission, (21511100401); Science and Technology Innovation Plan Of Shanghai Science and Technology Commission | AA11: This work was supported by the Chinese NSF Major Research Plan (No.92270121), Youth Fund (No.62102095), Shanghai Science and Technology Innovation Action Plan (No.21511100401). | AB11: Bekoulis G., Deleu J., Demeester T., Develder C., Joint entity recognition and relation extraction as a multi-head selection problem, Expert Systems with Applications, 114, pp. 34-45, (2018); Bi Z., Chen J., Jiang Y., Xiong F., Guo W., Chen H., Zhang N., CodeKGC: Code Language Model for Generative Knowledge Graph Construction, ACM Transactions on Asian and Low-Resource Language Information Processing, (2023); Bousmalis K., Vezzani G., Rao D., Devin C., Lee A.X., Bauza M., Davchev T., Zhou Y., Gupta A., Raju A.S., Laurens A., Fantacci C., Dalibard V., Zambelli M., Fernandes Martins M., Pevceviciute R., Blokzijl M., Denil M., Batchelor N., Lampe T., Parisotto E., Zolna K., Reed S.E., Gomez Colmenarejo S., Scholz J., Abdolmaleki A., Groth O., Regli J., Sushkov O.O., Rothorl T., Enrique Chen J., Aytar Y., Barker D., Ortiz J., Riedmiller M.A., Tobias Springenberg J., Hadsell R., Nori F., Manfred Otto Heess N., RoboCat: A Self-Improving Generalist Agent for Robotic Manipulation, (2023); Chen B., Shu C., Shareghi E., Collier N., Narasimhan K., Yao S., FireAct: Toward Language Agent Fine-tuning, (2023); Chung H., Hou L., Longpre S., Zoph B., Tay Y., Fedus W., Li E., Wang X., Dehghani M., Brahma S., Webson A., Shane Gu S., Dai Z., Suzgun M., Chen X., Chowdhery A., Valter D., Narang S., Mishra G., Wei Yu A., Zhao V., Huang Y., Dai A.M., Yu H., Petrov S., Huai Hsin Chi E., Dean J., Devlin J., Roberts A., Zhou D., Le Q.V., Wei J., Scaling Instruction-Finetuned Language Models, (2022); Gao T., Yao X., Chen D., SimCSE: Simple Contrastive Learning of Sentence Embeddings, Conference on Empirical Methods in Natural Language Processing, (2021); Guo D., Zhu Q., Yang D., Xie Z., Dong K., Zhang W., Chen G., Bi X., Wu Y., Li Y.K., Luo F., Xiong Y., Liang W., DeepSeek-Coder: When the Large Language Model Meets Programming-The Rise of Code Intelligence, (2024); Guo Y., Li Z., Jin X., Liu Y., Zeng Y., Liu W., Li X., Yang P., Bai L., Guo J., Cheng X., Retrieval-Augmented Code Generation for Universal Information Extraction, (2023); Hu E.J., Shen Y., Wallis P., Allen-Zhu Z., Li Y., Wang S., Wang L., Chen W., LoRA: Low-Rank Adaptation of Large Language Models, International Conference on Learning Representations (ICLR), (2022); Li P., Sun T., Tang Q., Yan H., Wu Y., Huang X., Qiu X., CodeIE: Large Code Generation Models are Better Few-Shot Information Extractors, (2023); Li S., He W., Shi Y., Jiang W., Liang H., Jiang Y., Zhang Y., Lyu Y., Zhu Y., DuIE: A Large-Scale Chinese Dataset for Information Extraction, Natural Language Processing and Chinese Computing, (2019); Li X., Yin F., Sun Z., Li X., Yuan A., Chai D., Zhou M., Li J., Entity-Relation Extraction as Multi-Turn Question Answering, (2019); Liu Y., Ott M., Goyal N., Du J., Joshi M., Chen D., Levy O., Lewis M., Zettlemoyer L., Stoyanov V., Roberta: A robustly optimized bert pretraining approach, (2019); Loshchilov I., Hutter F., DecoupledWeight Decay Regularization, International Conference on Learning Representations, (2017); Lou J., Lu Y., Dai D., Jia W., Lin H., Han X., Sun L., Wu H., Universal Information Extraction as Unified Semantic Matching, Proceedings of the AAAI Conference on Artificial Intelligence, 37, 11, pp. 13318-13326, (2023); Lu Y., Liu Q., Dai D., Xiao X., Lin H., Han X., Sun L., Wu H., Unified structure generation for universal information extraction, (2022); Luan Y., He L., Ostendorf M., Hajishirzi H., Multi-Task Identification of Entities, Relations, and Coreference for Scientific Knowledge Graph Construction, Conference on Empirical Methods in Natural Language Processing, (2018); Qiao S., Zhang N., Fang R., Luo Y., Zhou W., Eleanor Jiang Y., Lv C., Chen H., AUTOACT: Automatic Agent Learning from Scratch via Self-Planning, (2024); Raffel C., Shazeer N., Roberts A., Lee K., Narang S., Matena M., Zhou Y., Li W., Liu P.J., Exploring the limits of transfer learning with a unified text-to-text transformer, The Journal of Machine Learning Research, 21, 1, pp. 5485-5551, (2020); Enrique Ramos J., Using TF-IDF to Determine Word Relevance in Document Queries, (2003); Robertson S.E., Zaragoza H., The Probabilistic Relevance Framework: BM25 and beyond, Found. Trends Inf. Retr., 3, pp. 333-389, (2009); Sumers T.R., Yao S., Narasimhan K., Griffiths T.L., Cognitive architectures for language agents, (2023); Touvron H., Martin L., Stone K.R., Albert P., Almahairi A., Babaei Y., Bashlykov N., Batra S., Bhargava P., Bhosale S., Bikel D.M., Blecher L., Canton Ferrer C., Chen M., Cucurull G., Esiobu D., Fernandes J., Fu J., Fu W., Fuller B., Gao C., Goswami V., Goyal N., Hartshorn A., Hosseini S., Hou R., Inan H., Kardas M., Kerkez V., Khabsa M., Kloumann I.M., Korenev A., Singh Koura P., Lachaux M., Lavril T., Lee J., Liskovich D., Lu Y., Mao Y., Martinet X., Mihaylov T., Mishra P., Molybog I., Nie Y., Poulton A., Reizenstein J., Rungta R., Saladi K., Schelten A., Silva R., Michael Smith E., Subramanian R., Tan X., Tang B., Taylor R., Williams A., Xiang Kuan J., Xu P., Yan Z., Zarov I., Zhang Y., Fan A., Kambadur M., Narang S., Rodriguez A., Stojnic R., Edunov S., Scialom T., Llama 2: Open Foundation and Fine-Tuned Chat Models, (2023); Ulmer D., Mansimov E., Lin K., Sun J., Gao X., Zhang Y., Bootstrapping LLM-based Task-Oriented Dialogue Agents via Self-Talk, (2024); Wan Z., Cheng F., Mao Z., Liu Q., Song H., Li J., Kurohashi S., GPT-RE: In-context Learning for Relation Extraction using Large Language Models, (2023); Wang L., Ma C., Feng X., Zhang Z., Yang H., Zhang J., Chen Z., Tang J., Chen X., Lin Y., Xin Zhao W., Wei Z., Wen J., A Survey on Large Language Model based Autonomous Agents, (2023); Wang X., Zhou W., Zu C., Xia H., Chen T., Zhang Y., Zheng R., Ye J., Zhang Q., Gui T., Kang J., Yang J., Li S., Du C., InstructUIE: Multi-task Instruction Tuning for Unified Information Extraction, (2023); Wang Y., Yu B., Zhang Y., Liu T., Zhu H., Sun L., TPLinker: Single-stage joint extraction of entities and relations through token pair linking, (2020); Wei X., Cui X., Cheng N., Wang X., Zhang X., Huang S., Xie P., Xu J., Chen Y., Zhang M., Jiang Y., Han W., Zero-Shot Information Extraction via Chatting with ChatGPT, (2023); Wu L., Zheng Z., Qiu Z., Wang H., Gu H., Shen T., Qin C., Zhu C., Zhu H., Liu Q., Xiong H., Chen E., A Survey on Large Language Models for Recommendation, (2023); Xiao S., Liu Z., Zhang P., Muennighoff N., CPack: Packaged Resources To Advance General Chinese Embedding, (2023); Xu D., Chen W., Peng W., Zhang C., Xu T., Zhao X., Wu X., Zheng Y., Chen E., Large Language Models for Generative Information Extraction: A Survey, (2023); Yao S., Zhao J., Yu D., Shafran I., Narasimhan K.R., Cao Y., ReAct: Synergizing Reasoning and Acting in Language Models, NeurIPS 2022 Foundation Models for Decision Making Workshop, (2022); Ye H., Gui H., Zhang A., Liu T., Hua W., Jia W., Beyond Isolation: Multi-Agent Synergy for Improving Knowledge Graph Construction, (2023); Yu B., Zhang Z., Shu X., Wang Y., Liu T., Wang B., Li S., Joint extraction of entities and relations based on a novel decomposition strategy, (2019); Zhang K., Jimenez Gutierrez B., Su Y., Aligning Instruction Tasks Unlocks Large Language Models as Zero-Shot Relation Extractors, Findings of the Association for Computational Linguistics: ACL 2023, pp. 794-812, (2023); Xin Zhao W., Zhou K., Li J., Tang T., Wang X., Hou Y., Min Y., Zhang B., Zhang J., Dong Z., Du Y., Yang C., Chen Y., Chen Z., Jiang J., Ren R., Li Y., Tang X., Liu Z., Liu P., Nie J., Rong Wen J., A Survey of Large Language Models, (2023); Zhou S., Bowen Y., Sun A., Long C., Li J., Yu H., Sun J., A Survey on Neural Open Information Extraction: Current Status and Future Directions, (2022); Zhou W., Zhang S., Gu Y., Chen M., Poon H., UniversalNER: Targeted Distillation from Large Language Models for Open Named Entity Recognition, The Twelfth International Conference on Learning Representations, (2024); Zhou Y., Shen T., Geng X., Long G., Jiang D., ClarET: Pre-training a Correlation-Aware Context-To-Event Transformer for Event-Centric Generation and Classification, (2022); Zhu Y., Qiao S., Ou Y., Deng S., Zhang N., Lyu S., Shen Y., Liang L., Gu J., Chen H., KnowAgent: Knowledge-Augmented Planning for LLM-Based Agents, (2024); Zhu Y., Wang X., Chen J., Qiao S., Ou Y., Yao Y., Deng S., Chen H., Zhang N., LLMs for Knowledge Graph Construction and Reasoning: Recent Capabilities and Future Opportunities, (2023) | AC11: D. Yang; School of Data Science, Fudan University, Shanghai, China; email: yangdeqing@fudan.edu.cn | AE11: Association for Computing Machinery | AF11: ACM SIGIR; ACM SIGWEB | AG11: 33rd ACM International Conference on Information and Knowledge Management, CIKM 2024 | AH11: 21 October 2024 through 25 October 2024 | AI11: Boise | AJ11: 203771.0 | AK11: 21550751 | AL11: 979-840070436-9 | AO11: English | AP11: Int Conf Inf Knowledge Manage | AQ11: Conference paper | AR11: Final | AS11: All Open Access; Green Open Access | AT11: Scopus | AU11: 2-s2.0-85210024610 | AV11: q1 | AW11: Scopus | AX11: TRUE | AY11: =IF(AX11=TRUE,1,IF(AX11=FALSE,0,-1)) -> 1 | AZ11: ? | BA11: =IF(AZ11=TRUE,1,IF(AZ11=FALSE,0,-1)) -> -1 | BB11: ? | BC11: =IF(BB11=TRUE,1,IF(BB11=FALSE,0,-1)) -> -1 | BD11: 1 | BE11: 1 | BF11: 1 | BG11: 1 | BH11: =IF(BG11=1,"Yes",IF(BG11=-1,"Doubt","No")) -> Yes | BI11: =IF(BF11=1,"Yes","No") -> Yes | BJ11: 1 | BK11: Multilingual approach with LLMs to extract information. Agents.
A12: 38 | B12: Bai G.; Lu C.; Geng J.; Li S.; Shi Y.; Liu X.; Liu Y.; Zhang Z.; Liu R. | C12: Bai, Ge (58705641200); Lu, Chenji (58846896500); Geng, Jiaxiang (57919995000); Li, Shilong (58846970400); Shi, Yidong (58137649700); Liu, Xiyan (58681086500); Liu, Ying (59449583200); Zhang, Zhang (57798727500); Liu, Ruifang (55975558800) | D12: 58705641200; 58846896500; 57919995000; 58846970400; 58137649700; 58681086500; 59449583200; 57798727500; 55975558800 | E12: Always the Best Fit: Adaptive Domain Gap Filling from Causal Perspective for Few-Shot Relation Extraction | F12: 2023.0 | G12: Findings of the Association for Computational Linguistics: EMNLP 2023 | K12: 10533.0 | L12: 10542.0 | M12: 9.0 | N12: 1.0 | P12: https://www.scopus.com/inward/record.uri?eid=2-s2.0-85183293428&partnerID=40&md5=645b3a6501b5fb6fbd3afc9ea4a592ae | Q12: Beijing University of Posts and Telecommunications, China | R12: Bai G., Beijing University of Posts and Telecommunications, China; Lu C., Beijing University of Posts and Telecommunications, China; Geng J., Beijing University of Posts and Telecommunications, China; Li S., Beijing University of Posts and Telecommunications, China; Shi Y., Beijing University of Posts and Telecommunications, China; Liu X., Beijing University of Posts and Telecommunications, China; Liu Y., Beijing University of Posts and Telecommunications, China; Zhang Z., Beijing University of Posts and Telecommunications, China; Liu R., Beijing University of Posts and Telecommunications, China | S12: Cross-domain Relation Extraction aims to transfer knowledge from a source domain to a different target domain to address low-resource challenges. However, the semantic gap caused by data bias between domains is a major challenge, especially in few-shot scenarios. Previous work has mainly focused on transferring knowledge between domains through shared feature representations without analyzing the impact of each factor that may produce data bias based on the characteristics of each domain. This work takes a causal perspective and proposes a new framework CausalGF. By constructing a unified structural causal model, we estimate the causal effects of factors such as syntactic structure, label distribution, and entities on the outcome. CausalGF calculates the causal effects among the factors and adjusts them dynamically based on domain characteristics, enabling adaptive gap filling. Our experiments show that our approach better fills the domain gap, yielding significantly better results on the cross-domain few-shot relation extraction task. ¬© 2023 Association for Computational Linguistics. | U12: Computational linguistics; Extraction; Syntactics; Best fit; Causal modeling; Cross-domain; Effect of factors; Feature representation; Gap filling; Relation extraction; Semantic gap; Syntactic structure; Target domain; Semantics | AB12: Abbasnejad Ehsan, Teney Damien, Parvaneh Amin, Shi Javen, van den Hengel Anton, Counterfactual vision and language learning, Proceedings of the IEEE/CVF conference on computer vision and pattern recognition, pp. 10044-10054, (2020); Soares Livio Baldini, FitzGerald Nicholas, Ling Jeffrey, Kwiatkowski Tom, Matching the blanks: Distributional similarity for relation learning, Proceedings of the 57th Annual Meeting of the Association for Computational Linguistics, (2019); Bassignana Elisa, Plank Barbara, CrossRE: A cross-domain dataset for relation extraction, Findings of the Association for Computational Linguistics: EMNLP 2022, (2022); Cong Xin, Yu Bowen, Liu Tingwen, Cui Shiyao, Tang Hengzhu, Wang Bin, Inductive unsupervised domain adaptation for few-shot classification via clustering, Machine Learning and Knowledge Discovery in Databases: European Conference, ECML PKDD 2020, pp. 624-639, (2021); Devlin Jacob, Chang Ming-Wei, Lee Kenton, Toutanova Kristina, BERT: Pre-training of deep bidirectional transformers for language understanding, Proceedings of the 2019 Conference of the North American Chapter of the Association for Computational Linguistics, (2019); Feng Fuli, Zhang Jizhi, He Xiangnan, Zhang Hanwang, Chua Tat-Seng, Empowering language understanding with counterfactual reasoning, Findings of the Association for Computational Linguistics: ACL-IJCNLP 2021, pp. 2226-2236, (2021); Finn Chelsea, Abbeel Pieter, Levine Sergey, Model-agnostic meta-learning for fast adaptation of deep networks, International conference on machine learning, pp. 1126-1135, (2017); Ganin Yaroslav, Ustinova Evgeniya, Ajakan Hana, Germain Pascal, Larochelle Hugo, Laviolette Francois, Marchand Mario, Lempitsky Victor, Domain-adversarial training of neural networks, The journal of machine learning research, 17, 1, (2016); Gao Hang, Shou Zheng, Zareian Alireza, Zhang Hanwang, Chang Shih-Fu, Low-shot learning via covariance-preserving adversarial augmentation networks, Advances in Neural Information Processing Systems, 31, (2018); Gao Tianyu, Han Xu, Zhu Hao, Liu Zhiyuan, Li Peng, Sun Maosong, Zhou Jie, FewRel 2.0: Towards more challenging few-shot relation classification, Proceedings of EMNLP-IJCNLP, (2019); Glymour Madelyn, Pearl Judea, Jewell Nicholas P, Causal inference in statistics: A primer, (2016); Han Jiale, Cheng Bo, Lu Wei, Exploring task difficulty for few-shot relation extraction, Proceedings of the 2021 Conference on EMNLP, (2021); Han Xu, Zhu Hao, Yu Pengfei, Wang Ziyun, Yao Yuan, Liu Zhiyuan, Sun Maosong, FewRel: A large-scale supervised few-shot relation classification dataset with state-of-the-art evaluation, Proceedings of the 2018 Conference on Empirical Methods in Natural Language Processing, (2018); He Kai, Huang Yucheng, Mao Rui, Gong Tieliang, Li Chen, Cambria Erik, Virtual prompt pretraining for prototype-based few-shot relation extraction, Expert Systems with Applications, 213, (2023); Hochreiter Sepp, Schmidhuber Jurgen, Long short-term memory, Neural Computation, 9, 8, pp. 1735-1780, (1997); Liu Fangchao, Lin Hongyu, Han Xianpei, Cao Boxi, Sun Le, Pre-training to match for unified low-shot relation extraction, Proceedings of the 60th Annual Meeting of the Association for Computational Linguistics, (2022); Morgan Stephen L., Winship Christopher, Counterfactuals and Causal Inference: Methods and Principles for Social Research, 2 edition, Analytical Methods for Social Research, (2014); Nan Guoshun, Zeng Jiaqi, Qiao Rui, Guo Zhijiang, Lu Wei, Uncovering main causalities for long-tailed information extraction, CoRR, (2021); Pearl Judea, Causality, (2009); Pearl Judea, Et al., Models, reasoning and inference, 19, 2, (2000); Peng Yifan, Chen Qingyu, Lu Zhiyong, An empirical study of multi-task learning on BERT for biomedical text mining, Proceedings of the 19th SIGBioMed Workshop on Biomedical Language Processing, (2020); Shen Jian, Qu Yanru, Zhang Weinan, Yu Yong, Wasserstein distance guided representation learning for domain adaptation, Proceedings of the AAAI Conference on Artificial Intelligence, 32, (2018); Shi Ge, Feng Chong, Huang Lifu, Zhang Boliang, Ji Heng, Liao Lejian, Huang He-Yan, Genre separation network with adversarial training for cross-genre relation extraction, Proceedings of the 2018 Conference on Empirical Methods in Natural Language Processing, pp. 1018-1023, (2018); Snell Jake, Swersky Kevin, Zemel Richard, Prototypical networks for few-shot learning, Advances in Neural Information Processing Systems, 30, (2017); Tang Kaihua, Niu Yulei, Huang Jianqiang, Shi Jiaxin, Zhang Hanwang, Unbiased scene graph generation from biased training, Proceedings of the IEEE/CVF conference on computer vision and pattern recognition, pp. 3716-3725, (2020); Triantafillou Eleni, Zemel Richard, Urtasun Raquel, Few-shot learning through an information retrieval lens, Advances in neural information processing systems, (2017); Van der Maaten Laurens, Hinton Geoffrey, Visualizing data using t-sne, Journal of machine learning research, 9, 11, (2008); Vaswani Ashish, Shazeer Noam, Parmar Niki, Uszkoreit Jakob, Jones Llion, Gomez Aidan N, Kaiser Lukasz, Polosukhin Illia, Attention is all you need, Advances in neural information processing systems, (2017); Wang Zhao, Culotta Aron, Robustness to spurious correlations in text classification via automatically generated counterfactuals, Proceedings of the AAAI Conference on Artificial Intelligence, 35, pp. 14024-14031, (2021); Wu Yiquan, Kuang Kun, Zhang Yating, Liu Xiaozhong, Sun Changlong, Xiao Jun, Zhuang Yueting, Si Luo, Wu Fei, De-biased court's view generation with causality, Proceedings of the 2020 Conference on Empirical Methods in Natural Language Processing (EMNLP), pp. 763-780, (2020); Wu Yu, Lin Yutian, Dong Xuanyi, Yan Yan, Ouyang Wanli, Yang Yi, Exploit the unknown gradually: One-shot video-based person re-identification by stepwise learning, Proceedings of the IEEE Conference on Computer Vision and Pattern Recognition (CVPR), (2018); Yamada Ikuya, Asai Akari, Shindo Hiroyuki, Takeda Hideaki, Matsumoto Yuji, LUKE: Deep contextualized entity representations with entity-aware self-attention, Proceedings of the 2020 Conference on Empirical Methods in Natural Language Processing (EMNLP), pp. 6442-6454, (2020); Yoo Donghyun, Fan Haoqi, Boddeti Vishnu, Kitani Kris, Efficient k-shot learning with regularized deep networks, Proceedings of the AAAI Conference on Artificial Intelligence, 32, (2018); Yuan Zhongju, Wang Zhenkun, Li Genghui, Cross-domain few-shot relation extraction via representation learning and domain adaptation, (2022); Zeng Xiangji, Li Yunliang, Zhai Yuchen, Zhang Yin, Counterfactual generator: A weakly-supervised method for named entity recognition, Proceedings of the 2020 Conference on Empirical Methods in Natural Language Processing (EMNLP), pp. 7270-7280, (2020); Zhang Peiyuan, Lu Wei, Better few-shot relation extraction with label prompt dropout, Proceedings of the 2022 Conference on Empirical Methods in Natural Language Processing, (2022); Zhang Yuhao, Zhong Victor, Chen Danqi, Angeli Gabor, Manning Christopher D., Position-aware attention and supervised data improve slot filling, Proceedings of the 2017 Conference on Empirical Methods in Natural Language Processing, (2017); Zhang Zhengyan, Han Xu, Liu Zhiyuan, Jiang Xin, Sun Maosong, Liu Qun, ERNIE: Enhanced language representation with informative entities, Proceedings of ACL, (2019) | AE12: Association for Computational Linguistics (ACL) | AF12: Apple; Colossal-AI; et al.; Google Research; GTCOM; King Salman Global Academy for Arabic Language | AG12: 2023 Findings of the Association for Computational Linguistics: EMNLP 2023 | AH12: 6 December 2023 through 10 December 2023 | AI12: Singapore | AJ12: 196127.0 | AL12: 979-889176061-5 | AO12: English | AP12: Find. Assoc. Comput. Linguist.: EMNLP | AQ12: Conference paper | AR12: Final | AT12: Scopus | AU12: 2-s2.0-85183293428 | AV12: q1 | AW12: Scopus | AX12: TRUE | AY12: =IF(AX12=TRUE,1,IF(AX12=FALSE,0,-1)) -> 1 | AZ12: TRUE | BA12: =IF(AZ12=TRUE,1,IF(AZ12=FALSE,0,-1)) -> 1 | BB12: TRUE | BC12: =IF(BB12=TRUE,1,IF(BB12=FALSE,0,-1)) -> 1 | BD12: 1 | BE12: 1 | BF12: 0 | BG12: 0 | BH12: =IF(BG12=1,"Yes",IF(BG12=-1,"Doubt","No")) -> No | BI12: =IF(BF12=1,"Yes","No") -> No | BJ12: 0 | BK12: Semantic similarity full based. Dynamic domains and how to adaptate the same model to each one.
A13: 107 | B13: Yang X.; Zhang X.; Zuo J.; Wilson S.; Petzold L. | C13: Yang, Xianjun (57467893700); Zhang, Xinlu (57222956421); Zuo, Julia (57210283219); Wilson, Stephen (55612462800); Petzold, Linda (7005581592) | D13: 57467893700; 57222956421; 57210283219; 55612462800; 7005581592 | E13: An Analysis of Relation Extraction within Sentences from Wet Lab Protocols | F13: 2021.0 | G13: Proceedings - 2021 IEEE International Conference on Big Data, Big Data 2021 | K13: 562.0 | L13: 570.0 | M13: 8.0 | N13: 1.0 | O13: 10.1109/BigData52589.2021.9671781 | P13: https://www.scopus.com/inward/record.uri?eid=2-s2.0-85125359405&doi=10.1109%2fBigData52589.2021.9671781&partnerID=40&md5=ccc49e5ca02bea94af56d2f693e97259 | Q13: University of California, Santa Barbara, Department of Computer Science, Santa Barbara, United States; Materials Department, Santa Barbara, University of California, Santa Barbara, United States | R13: Yang X., University of California, Santa Barbara, Department of Computer Science, Santa Barbara, United States; Zhang X., University of California, Santa Barbara, Department of Computer Science, Santa Barbara, United States; Zuo J., Materials Department, Santa Barbara, University of California, Santa Barbara, United States; Wilson S., Materials Department, Santa Barbara, University of California, Santa Barbara, United States; Petzold L., University of California, Santa Barbara, Department of Computer Science, Santa Barbara, United States | S13: Wet lab protocols (WLPs) are sets of instructions written in domain-specific natural language for step-by-step biological experimental processes. There have been efforts to annotate WLPs for shallow semantic parsing to enable reproducible procedures, text mining, and automatic conversion into a machine-readable format. However, current methods have not fully exploited the relation extraction sub-task on the protocol corpus. Neural approaches have the potential to deal with the various noise and in-domain jargon in the texts. To explore the viability of neural methods for this task, we perform a thorough analysis of both graph and nongraph neural approaches. We find that both graph neural networks with generated parameters (GP-GNNs) and Context-Aware models show advantages in relation extraction and are well suited to our goal. Specifically, the GP-GNNs and Context-Aware models demonstrate similar performance on all three WLPs datasets when the full training set is used, both outperforming the previous best results significantly. This can be explained by the observation that considering multiple relations in a sentence enhances the predictive ability. In addition, our extensive experiments demonstrate that the Context-Aware approach in particular can achieve good results even with a limited amount of training data, providing new insights for low-resource scenarios. ¬© 2021 IEEE. | T13: Context-Aware; Graph neural networks; Relation extraction; Text mining; Wet lab protocols | U13: Data mining; Extraction; Natural language processing systems; Semantics; Syntactics; Context-Aware; Context-aware models; Domain specific; Graph neural networks; Lab protocols; Natural languages; Relation extraction; Shallow semantic parsing; Text-mining; Wet lab protocol; Graph neural networks | Z13: UC Santa Barbara NSF; National Science Foundation, NSF, (DMR-1906325); National Science Foundation, NSF | AA13: Funding text 1: This work is supported by UC Santa Barbara NSF Quantum Foundry funded via the Q-AMASE-i program under NSF award DMR-1906325.; Funding text 2: We gratefully acknowledge support from the UC Santa Barbara NSF Quantum Foundry funded via the Q-AMASE-i program under NSF award DMR-1906325. Any opinion or conclusions expressed in this material are those of the author(s) and do not necessarily reflect the views of the National Science Foundation. | AB13: Grishman R., Adaptive information extraction and sublanguage analysis, Proc. of IJCAI 2001, pp. 1-4, (2001); Grishman R., Kittredge R., Analyzing Language in Restricted Domains: Sublanguage Description and Processing, (2014); Kulkarni C., Xu W., Ritter A., Machiraju R., An Annotated Corpus for Machine Reading of Instructions in Wet Lab Protocols, (2018); King R.D., Rowland J., Oliver S.G., Young M., Aubrey W., Byrne E., Liakata M., Markham M., Pir P., Soldatova L.N., Et al., The automation of science, Science, 324, 5923, pp. 85-89, (2009); Soldatova L.N., Nadis D., King R.D., Basu P.S., Haddi E., Baumle V., Saunders N.J., Marwan W., Rudkin B.B., Exact2: The semantics of biomedical protocols, BMC Bioinformatics, 15, 14, pp. 1-11, (2014); Vasilev V., Liu C., Haddock T., Bhatia S., Adler A., Yaman F., Beal J., Babb J., Weiss R., Densmore D., Et al., A software stack for specification and robotic execution of protocols for synthetic biological engineering, 3rd International Workshop on Bio-design Automation, (2011); Shatkay H., Feldman R., Mining the biomedical literature in the genomic era: An overview, Journal of Computational Biology, 10, 6, pp. 821-855, (2003); Tafti A.P., Badger J., LaRose E., Shirzadi E., Mahnke A., Mayer J., Ye Z., Page D., Peissig P., Adverse drug event discovery using biomedical literature: A big data neural network adventure, JMIR Medical Informatics, 5, 4, (2017); Cano G., Garcia-Rodriguez J., Garcia-Garcia A., Perez-Sanchez H., Benediktsson J.A., Thapa A., Barr A., Automatic selection of molecular descriptors using random forest: Application to drug discovery, Expert Systems with Applications, 72, pp. 151-159, (2017); Bollini M., Tellex S., Thompson T., Roy N., Rus D., Interpreting and executing recipes with a cooking robot, Experimental Robotics, pp. 481-495, (2013); Bates M., Berliner A.J., Lachoff J., Jaschke P.R., Groban E.S., Wet lab accelerator: A web-based application democratizing laboratory automation for synthetic biology, ACS Synthetic Biology, 6, 1, pp. 167-171, (2017); Kim E., Huang K., Saunders A., McCallum A., Ceder G., Olivetti E., Materials synthesis insights from scientific literature via text extraction and machine learning, Chemistry of Materials, 29, 21, pp. 9436-9444, (2017); Swarup D., Bajaj A., Mysore S., O'Gorman T., Das R., Mc-Callum A., An instance level approach for shallow semantic parsing in scientific procedural text, Proceedings of the 2020 Conference on Empirical Methods in Natural Language Processing: Findings, pp. 3010-3017, (2020); Friedrich A., Adel H., Tomazic F., Hingerl J., Benteau R., Marusczyk A., Lange L., The sofc-exp corpus and neural approaches to information extraction in the materials science domain, Proceedings of the 58th Annual Meeting of the Association for Computational Linguistics, pp. 1255-1268, (2020); Kulkarni C., Chan J., Fosler-Lussier E., Machiraju R., Learning latent structures for cross action phrase relations in wet lab protocols, Proceedings of the 59th Annual Meeting of the Association for Computational Linguistics and the 11th International Joint Conference on Natural Language Processing, pp. 6737-6750, (2021); Tabassum J., Lee S., Xu W., Ritter A., Wnut-2020 Task 1 Overview: Extracting Entities and Relations from Wet Lab Protocols, (2020); Borthwick A.E., A Maximum Entropy Approach to Named Entity Recognition, (1999); Kambhatla N., Combining lexical, syntactic, and semantic features with maximum entropy models for information extraction, Proceedings of the ACL Interactive Poster and Demonstration Sessions, pp. 178-181, (2004); Devlin J., Chang M.-W., Lee K., Toutanova K., Bert: Pre-training of Deep Bidirectional Transformers for Language Understanding, (2018); Sorokin D., Gurevych I., Context-aware representations for knowledge base relation extraction, Proceedings of the 2017 Conference on Empirical Methods in Natural Language Processing, pp. 1784-1789, (2017); Zhu H., Lin Y., Liu Z., Fu J., Chua T.-S., Sun M., Graph Neural Networks with Generated Parameters for Relation Extraction, (2019); Zhang Y., Chen Q., Yang Z., Lin H., Lu Z., Biowordvec, improving biomedical word embeddings with subword information and mesh, Scientific Data, 6, 1, pp. 1-9, (2019); Moen S., Ananiadou T.S.S., Distributional semantics resources for biomedical text processing, Proceedings of LBM, pp. 39-44, (2013); Pedregosa F., Varoquaux G., Gramfort A., Michel V., Thirion B., Grisel O., Blondel M., Prettenhofer P., Weiss R., Dubourg V., Et al., Scikit-learn: Machine learning in python, The Journal of Machine Learning Research, 12, pp. 2825-2830, (2011); Sohrab M.G., Nguyen A.-K.D., Miwa M., Takamura H., Mgsohrab at wnut 2020 shared task-1: Neural exhaustive approach for entity and relation recognition over wet lab protocols, Proceedings of the Sixth Workshop on Noisy User-generated Text (W-NUT 2020), pp. 290-298, (2020); Zeng D., Liu K., Lai S., Zhou G., Zhao J., Relation classification via convolutional deep neural network, Proceedings of COLING 2014, the 25th International Conference on Computational Linguistics: Technical Papers, pp. 2335-2344, (2014); Zeng D., Liu K., Chen Y., Zhao J., Distant supervision for relation extraction via piecewise convolutional neural networks, Proceedings of the 2015 Conference on Empirical Methods in Natural Language Processing, pp. 1753-1762, (2015); Muneeb T., Sahu S., Anand A., Evaluating distributed word representations for capturing semantics of biomedical concepts, Proceedings of BioNLP, 15, pp. 158-163, (2015); Hochreiter S., Schmidhuber J., Long short-term memory, Neural Computation, 9, 8, pp. 1735-1780, (1997); Schlichtkrull M., Kipf T.N., Bloem P., Berg Den Van R., Titov I., Welling M., Modeling relational data with graph convolutional networks, European Semantic Web Conference, pp. 593-607, (2018); Zhang Y., Qi P., Manning C.D., Graph Convolution over Pruned Dependency Trees Improves Relation Extraction, (2018); Sahu S.K., Christopoulou F., Miwa M., Ananiadou S., Intersentence Relation Extraction with Document-level Graph Convolutional Neural Network, (2019); Luan Y., Wadden D., He L., Shah A., Ostendorf M., Hajishirzi H., A General Framework for Information Extraction Using Dynamic Span Graphs, (2019); Kingma D.P., Ba J., Adam: A Method for Stochastic Optimization, (2014); Gu Y., Tinn R., Cheng H., Lucas M., Usuyama N., Liu X., Naumann T., Gao J., Poon H., Domain-specific Language Model Pretraining for Biomedical Natural Language Processing, (2020); Mysore S., Jensen Z., Kim E., Huang K., Chang H.-S., Strubell E., Flanigan J., McCallum A., Olivetti E., The Materials Science Procedural Text Corpus: Annotating Materials Synthesis Procedures with Shallow Semantic Structures, (2019); Chen Y., Wang D.Z., Goldberg S., Scalekb: Scalable learning and inference over large knowledge bases, The VLDB Journal, 25, 6, pp. 893-918, (2016) | AD13: Chen Y.; Ludwig H.; Tu Y.; Fayyad U.; Zhu X.; Hu X.T.; Byna S.; Liu X.; Zhang J.; Pan S.; Papalexakis V.; Wang J.; Cuzzocrea A.; Ordonez C. | AE13: Institute of Electrical and Electronics Engineers Inc. | AF13: Ankura Collaboration Drives Results; IEEE; IEEE Computer Society; Lyve Cloud; NSF; Seagate | AG13: 2021 IEEE International Conference on Big Data, Big Data 2021 | AH13: 15 December 2021 through 18 December 2021 | AI13: Virtual, Online | AJ13: 176404.0 | AL13: 978-166543902-2 | AO13: English | AP13: Proc. - IEEE Int. Conf. Big Data, Big Data | AQ13: Conference paper | AR13: Final | AT13: Scopus | AU13: 2-s2.0-85125359405 | AV13: q1 | AW13: Scopus | AX13: ? | AY13: =IF(AX13=TRUE,1,IF(AX13=FALSE,0,-1)) -> -1 | AZ13: TRUE | BA13: =IF(AZ13=TRUE,1,IF(AZ13=FALSE,0,-1)) -> 1 | BB13: TRUE | BC13: =IF(BB13=TRUE,1,IF(BB13=FALSE,0,-1)) -> 1 | BD13: 1 | BE13: 1 | BF13: 0 | BG13: 0 | BH13: =IF(BG13=1,"Yes",IF(BG13=-1,"Doubt","No")) -> No | BI13: =IF(BF13=1,"Yes","No") -> No | BJ13: 0 | BK13: Use of GNNs. Either title either abstract exhibits alignment with the paper's scope; generative approaches. Biomedical domain with wet labs protocol.
A14: 32 | B14: Zhao J.; Hu Y.; Xu N.; Gui T.; Zhang Q.; Chen Y.; Gao X. | C14: Zhao, Jun (58846765100); Hu, Yuan (57222873035); Xu, Nuo (57211759176); Gui, Tao (57211256586); Zhang, Qi (57203621188); Chen, Yunwen (57210823603); Gao, Xiang (57751035600) | D14: 58846765100; 57222873035; 57211759176; 57211256586; 57203621188; 57210823603; 57751035600 | E14: An Exploration of Prompt-Based Zero-Shot Relation Extraction Method | F14: 2022.0 | G14: 21st Chinese National Conference on Computational Linguistic, CCL 2022 | K14: 786.0 | L14: 797.0 | M14: 11.0 | N14: 3.0 | P14: https://www.scopus.com/inward/record.uri?eid=2-s2.0-85146370315&partnerID=40&md5=6f8a6912359c97dab018015e5d439b86 | Q14: School of Computer Science, Shanghai Key Laboratory of Intelligent Information Processing, Fudan University, Shanghai, China; DataGrand Information Technology (Shanghai) Co., Ltd., Shanghai, China | R14: Zhao J., School of Computer Science, Shanghai Key Laboratory of Intelligent Information Processing, Fudan University, Shanghai, China; Hu Y., School of Computer Science, Shanghai Key Laboratory of Intelligent Information Processing, Fudan University, Shanghai, China; Xu N., School of Computer Science, Shanghai Key Laboratory of Intelligent Information Processing, Fudan University, Shanghai, China; Gui T., School of Computer Science, Shanghai Key Laboratory of Intelligent Information Processing, Fudan University, Shanghai, China; Zhang Q., School of Computer Science, Shanghai Key Laboratory of Intelligent Information Processing, Fudan University, Shanghai, China; Chen Y., DataGrand Information Technology (Shanghai) Co., Ltd., Shanghai, China; Gao X., DataGrand Information Technology (Shanghai) Co., Ltd., Shanghai, China | S14: Zero-shot relation extraction is an important method for dealing with the newly emerging relations in the real world which lacks labeled data. However, the mainstream two-tower zero-shot methods usually rely on large-scale and in-domain labeled data of predefined relations. In this work, we view zero-shot relation extraction as a semantic matching task optimized by prompt-tuning, which still maintains superior generalization performance when the labeled data of predefined relations are extremely scarce. To maximize the efficiency of data exploitation, instead of directly fine-tuning, we introduce a prompt-tuning technique to elicit the existing relational knowledge in pre-trained language model (PLMs). In addition, very few relation descriptions are exposed to the model during training, which we argue is the performance bottleneck of two-tower methods. To break through the bottleneck, we model the semantic interaction between relational instances and their descriptions directly during encoding. Experiment results on two academic datasets show that (1) our method outperforms the previous state-of-the-art method by a large margin with different samples of predefined relations; (2) this advantage will be further amplified in the low-resource scenario. ¬© 2022 China National Conference on Computational Linguistics Published under Creative Commons Attribution 4.0 International License. | U14: Computational linguistics; Extraction; Large dataset; Zero-shot learning; Exposed to; Extraction method; Fine tuning; Generalization performance; Labeled data; Language model; Large-scales; Real-world; Relation extraction; Semantic matching; Semantics | AB14: Chen Chih-Yao, Li Cheng-Te, Zs-bert: Towards zero-shot relation extraction with attribute representation learning, (2021); Chen Qian, Zhu Xiaodan, Ling Zhen-Hua, Wei Si, Jiang Hui, Inkpen Diana, Enhanced LSTM for natural language inference, Proceedings of the 55th Annual Meeting of the Association for Computational Linguistics (Volume 1: Long Papers), pp. 1657-1668, (2017); Clark Kevin, Khandelwal Urvashi, Levy Omer, Manning Christopher D., What does BERT look at? an analysis of bert's attention, CoRR, (2019); Devlin Jacob, Chang Ming-Wei, Lee Kenton, Toutanova Kristina, Bert: Pre-training of deep bidirectional transformers for language understanding, (2018); Devlin Jacob, Chang Ming-Wei, Lee Kenton, Toutanova Kristina, BERT: Pre-training of deep bidirectional transformers for language understanding, Proceedings of the 2019 Conference of the North American Chapter of the Association for Computational Linguistics: Human Language Technologies, Volume 1 (Long and Short Papers), pp. 4171-4186, (2019); Ding Ning, Chen Yulin, Han Xu, Xu Guangwei, Xie Pengjun, Zheng Hai-Tao, Liu Zhiyuan, Li Juanzi, Kim Hong-Gee, Prompt-learning for fine-grained entity typing, (2021); Du Jinhua, Han Jingguang, Way Andy, Wan Dadong, Multi-level structured self-attentions for distantly supervised relation extraction, (2018); Goldberg Yoav, Assessing bert's syntactic abilities, CoRR, (2019); Han Xu, Zhu Hao, Yu Pengfei, Wang Ziyun, Yao Yuan, Liu Zhiyuan, Sun Maosong, Fewrel: A large-scale supervised few-shot relation classification dataset with state-of-the-art evaluation, Proceedings of the 2018 Conference on Empirical Methods in Natural Language Processing, pp. 4803-4809, (2018); Han Xu, Zhu Hao, Yu Pengfei, Wang Ziyun, Yao Yuan, Liu Zhiyuan, Sun Maosong, FewRel: A large-scale supervised few-shot relation classification dataset with state-of-the-art evaluation, Proceedings of the 2018 Conference on Empirical Methods in Natural Language Processing, pp. 4803-4809, (2018); Han Xu, Zhao Weilin, Ding Ning, Liu Zhiyuan, Sun Maosong, Ptr: Prompt tuning with rules for text classification, (2021); Hewitt John, Manning Christopher D., A structural probe for finding syntax in word representations, Proceedings of the 2019 Conference of the North American Chapter of the Association for Computational Linguistics: Human Language Technologies, Volume 1 (Long and Short Papers), pp. 4129-4138, (2019); Jawahar Ganesh, Sagot Benoit, Seddah Djame, What does BERT learn about the structure of language?, Proceedings of the 57th Annual Meeting of the Association for Computational Linguistics, pp. 3651-3657, (2019); Jiang Zhengbao, Xu Frank F., Araki Jun, Neubig Graham, How can we know what language models know?, Transactions of the Association for Computational Linguistics, 8, pp. 423-438, (2020); Levy Omer, Seo Minjoon, Choi Eunsol, Zettlemoyer Luke, Zero-shot relation extraction via reading comprehension, Proceedings of the 21st Conference on Computational Natural Language Learning (CoNLL 2017), pp. 333-342, (2017); Li Xiang Lisa, Liang Percy, Prefix-tuning: Optimizing continuous prompts for generation, (2021); Liu Pengfei, Yuan Weizhe, Fu Jinlan, Jiang Zhengbao, Hayashi Hiroaki, Neubig Graham, Pre-train, prompt, and predict: A systematic survey of prompting methods in natural language processing, (2021); Madotto Andrea, Wu Chien-Sheng, Fung Pascale, Mem2Seq: Effectively incorporating knowledge bases into end-to-end task-oriented dialog systems, Proceedings of the 56th Annual Meeting of the Association for Computational Linguistics (Volume 1: Long Papers), pp. 1468-1478, (2018); Obamuyide Abiola, Vlachos Andreas, Zero-shot relation classification as textual entailment, Proceedings of the First Workshop on Fact Extraction and VERification (FEVER), pp. 72-78, (2018); Peters Matthew E., Neumann Mark, Zettlemoyer Luke, Yih Wen-tau, Dissecting contextual word embeddings: Architecture and representation, Proceedings of the 2018 Conference on Empirical Methods in Natural Language Processing, pp. 1499-1509, (2018); Radford Alec, Narasimhan Karthik, Salimans Tim, Sutskever Ilya, Improving language understanding by generative pre-training, (2018); Soares Livio Baldini, FitzGerald Nicholas, Ling Jeffrey, Kwiatkowski Tom, Matching the blanks: Distributional similarity for relation learning, (2019); Tenney Ian, Xia Patrick, Chen Berlin, Wang Alex, Poliak Adam, Thomas McCoy R, Kim Najoung, Van Durme Benjamin, Bowman Sam, Das Dipanjan, Pavlick Ellie, What do you learn from context? probing for sentence structure in contextualized word representations, International Conference on Learning Representations, (2019); Tsimpoukelli Maria, Menick Jacob, Cabi Serkan, Eslami SM, Vinyals Oriol, Hill Felix, Multimodal few-shot learning with frozen language models, (2021); Wang Zhen, Zhang Jianwen, Feng Jianlin, Chen Zheng, Knowledge graph embedding by translating on hyperplanes, Proceedings of the AAAI Conference on Artificial Intelligence, 28, (2014); Wu Shanchan, He Yifan, Enriching pre-trained language model with entity information for relation classification, Proceedings of the 28th ACM international conference on information and knowledge management, pp. 2361-2364, (2019); Xiong Chenyan, Power Russell, Callan Jamie, Explicit semantic ranking for academic search via knowledge graph embedding, Proceedings of the 26th International Conference on World Wide Web, WWW'17, pp. 1271-1279, (2017); Zhang Yuhao, Zhong Victor, Chen Danqi, Angeli Gabor, Manning Christopher D., Position-aware attention and supervised data improve slot filling, Proceedings of the 2017 Conference on Empirical Methods in Natural Language Processing, pp. 35-45, (2017); Zhong Zexuan, Friedman Dan, Chen Danqi, Factual probing is [MASK]: Learning vs. learning to recall, Proceedings of the 2021 Conference of the North American Chapter of the Association for Computational Linguistics: Human Language Technologies, pp. 5017-5033, (2021); Zhou Peng, Shi Wei, Tian Jun, Qi Zhenyu, Li Bingchen, Hao Hongwei, Xu Bo, Attention-based bidirectional long short-term memory networks for relation classification, Proceedings of the 54th annual meeting of the association for computational linguistics (volume 2: Short papers), pp. 207-212, (2016) | AC14: T. Gui; School of Computer Science, Shanghai Key Laboratory of Intelligent Information Processing, Fudan University, Shanghai, China; email: tgui@fudan.edu.cn; Q. Zhang; School of Computer Science, Shanghai Key Laboratory of Intelligent Information Processing, Fudan University, Shanghai, China; email: qz@fudan.edu.cn | AE14: Chinese National Conference on Computational Linguistic (CCL) | AG14: 21st Chinese National Conference on Computational Linguistic, CCL 2022 | AH14: 14 October 2022 through 16 October 2022 | AI14: Nanchang | AJ14: 185497.0 | AO14: English | AP14: Chin. Natl. Conf. Comput. Linguist., CCL | AQ14: Conference paper | AR14: Final | AT14: Scopus | AU14: 2-s2.0-85146370315 | AV14: q1 | AW14: Scopus | AX14: TRUE | AY14: =IF(AX14=TRUE,1,IF(AX14=FALSE,0,-1)) -> 1 | AZ14: ? | BA14: =IF(AZ14=TRUE,1,IF(AZ14=FALSE,0,-1)) -> -1 | BB14: TRUE | BC14: =IF(BB14=TRUE,1,IF(BB14=FALSE,0,-1)) -> 1 | BD14: 1 | BE14: 1 | BF14: 1 | BG14: 1 | BH14: =IF(BG14=1,"Yes",IF(BG14=-1,"Doubt","No")) -> Yes | BI14: =IF(BF14=1,"Yes","No") -> Yes | BJ14: 1 | BK14: It speaks about semantic similarity between relation representations (instances) and context (descriptions). By other hand, use PLMs to do that. Full based on prompting. Zs re.
A15: 108 | B15: Nugumanova A.; Baiburin Y.; Apayev K. | C15: Nugumanova, Aliya (55864815200); Baiburin, Yerzhan (56111999400); Apayev, Kurmash (57184396000) | D15: 55864815200; 56111999400; 57184396000 | E15: An Intelligent Web-Service for Automatic Concept Map Generation | F15: 2022.0 | G15: Communications in Computer and Information Science | H15: 1573 CCIS | K15: 41.0 | L15: 44.0 | M15: 3.0 | N15: 0.0 | O15: 10.1007/978-3-031-15168-2_4 | P15: https://www.scopus.com/inward/record.uri?eid=2-s2.0-85137983555&doi=10.1007%2f978-3-031-15168-2_4&partnerID=40&md5=789995dd0ffbc4c37edac2633df5df4a | Q15: Sarsen Amanzholov East Kazakhstan University, Shakarim 148, Ust-Kamenogorsk, 070000, Kazakhstan; D. Serikbayev East Kazakhstan Technical University, Serikbayev 19, Ust-Kamenogorsk, 070000, Kazakhstan | R15: Nugumanova A., Sarsen Amanzholov East Kazakhstan University, Shakarim 148, Ust-Kamenogorsk, 070000, Kazakhstan; Baiburin Y., Sarsen Amanzholov East Kazakhstan University, Shakarim 148, Ust-Kamenogorsk, 070000, Kazakhstan; Apayev K., D. Serikbayev East Kazakhstan Technical University, Serikbayev 19, Ust-Kamenogorsk, 070000, Kazakhstan | S15: Automatic generation of concept maps from texts is yet another research challenge at the intersection of Natural Language Processing (NLP) and Knowledge Engineering, that has not been fully resolved. Concept maps are knowledge visualization tools representing texts at the conceptual level. They are intended to show systemic relations between key concepts of a given text and contribute to its deeper understanding and appreciation. In this work, we present a web service for automatic generation of concept maps. The service provides both a simple web interface and API access. It takes an input text in Kazakh, Russian or English languages and generates a concept map, using one of two existing algorithms at the user‚Äôs choice. Our service in a sense eliminates the need for human effort in creating concept maps, and can be useful in teaching, developing research, and exploring texts. In addition to the proposed web service, the contribution of our paper consists in the adaptation of the used algorithms originally developed for texts in English, to Kazakh, which is recognized as low resource language in NLP. ¬© 2022, The Author(s), under exclusive license to Springer Nature Switzerland AG. | T15: Automatic generation of concept maps; Concept map mining; Knowledge graph; Relation extraction; Web-service | U15: Application programming interfaces (API); Knowledge graph; Natural language processing systems; Websites; Automatic Generation; Automatic generation of concept map; Concept map mining; Concept maps; Knowledge graphs; Language processing; Natural languages; Relation extraction; Webs services; Web services | AB15: Novak J.D., Canas A., Theoretical origins of concept maps, how to construct them, and uses in education, Reflecting Educ, 3, 1, pp. 29-42, (2007); Liao Y., Et al., Knowledge graph and its applications in MOOC and SPOC, 2019 2Nd International Conference on Contemporary Education and Economic Development (CEED), pp. 301-305, (2019); Goyal N., Et al., CON2KG-a large-scale domain-specific knowledge graph, Proceedings of the 30Th ACM Conference on Hypertext and Social Media, pp. 287-288, (2019); Kertkeidkachorn N., Ichise R., An automatic knowledge graph creation framework from natural language text, IEICE Trans. Inf. Syst., 101, 1, pp. 90-98, (2018); Pellissier Tanon T., Vrandecic D., Schaffert S., Steiner T., Pintscher L., From freebase to Wikidata: The great migration, Proceedings of the 25Th International Conference on WWW, pp. 1419-1428, (2016); Tiddi I., Lecue F., Hitzler P., (eds.): Knowledge Graphs for Explainable Artificial Intelligence: Foundations, Applications and Challenges, 47, (2020); Bader S.R., Grangel-Gonzalez I., Nanjappa P., Vidal M.-E., Maleshkova M., A knowledge graph for Industry 4.0, ESWC 2020. LNCS, Vol. 12123, pp. 465-480, (2020); Razniewski S., Suchanek F., Nutt W., But what do we know?, Proceedings of the 5Th Workshop on Automated Knowledge Base Construction, pp. 40-44, (2016); Vaswani A., Et al., Attention is all you need, Proceedings of Advances in Neural Information Processing Systems, pp. 5998-6008, (2017); Kim T., Yun Y., Kim N., Deep learning-based knowledge graph generation for COVID-19, Sustainability, 13, 4, (2021); Yang X., Et al., Clinical Relation Extraction Using Transformer-Based Models. Arxiv Preprint Arxiv, 2107, (2021); Qiao B., Zou Z., Huang Y., Fang K., Zhu X., Chen Y., A joint model for entity and relation extraction based on BERT, Neural Comput. Appl., 34, pp. 3471-3481, (2021); Pang N., Qian L., Lyu W., Yang J.D., Transfer learning for scientific data chain extraction in small chemical corpus with joint BERT-CRF model, Proceedings of BIRNDL@ SIGIR, pp. 28-41, (2019); Fader A., Soderland S., Etzioni O., Identifying relations for open information extraction, Proceedings of the 2011 Conference on Empirical Methods in Natural Language Processing, pp. 1535-1545, (2011); Soares L.B., Fitzgerald N., Ling J., Kwiatkowski T., Matching the Blanks: Distributional Similarity for Relation Learning. Arxiv Preprint Arxiv, 1906, (2019) | AC15: A. Nugumanova; Sarsen Amanzholov East Kazakhstan University, Ust-Kamenogorsk, Shakarim 148, 070000, Kazakhstan; email: yalisha@yandex.kz | AD15: Burnaev E.; Ivanov S.; Panchenko A.; Ignatov D.I.; Kuznetsov S.O.; Khachay M.; Koltsova O.; Kutuzov A.; Loukachevitch N.; Napoli A.; Pardalos P.M.; Saram√§ki J.; Savchenko A.V.; Tsymbalov E.; Tutubalina E. | AE15: Springer Science and Business Media Deutschland GmbH | AG15: 10th International Conference on Analysis of Images, Social Networks, and Texts, AIST 2021 | AH15: 16 December 2021 through 18 December 2021 | AI15: Virtual, Online | AJ15: 282519.0 | AK15: 18650929 | AL15: 978-303115167-5 | AO15: English | AP15: Commun. Comput. Info. Sci. | AQ15: Conference paper | AR15: Final | AS15: Paid access | AT15: Scopus | AU15: 2-s2.0-85137983555 | AV15: q1 | AW15: Scopus | AX15: ? | AY15: =IF(AX15=TRUE,1,IF(AX15=FALSE,0,-1)) -> -1 | AZ15: TRUE | BA15: =IF(AZ15=TRUE,1,IF(AZ15=FALSE,0,-1)) -> 1 | BB15: ? | BC15: =IF(BB15=TRUE,1,IF(BB15=FALSE,0,-1)) -> -1 | BD15: 1 | BE15: 1 | BF15: 0 | BG15: -1 | BH15: =IF(BG15=1,"Yes",IF(BG15=-1,"Doubt","No")) -> Doubt | BI15: =IF(BF15=1,"Yes","No") -> No | BJ15: 0 | BK15: Concept map generation. Seems author are talking about triplet extraction for relations that are systematic bewteen two entitites.
A16: 129 | B16: Liu S.; Lu T.; Li K.; Liu W. | C16: Liu, Shu (56294764300); Lu, Tingting (59135039400); Li, Kaiwen (57224591772); Liu, Weihua (56604455300) | D16: 56294764300; 59135039400; 57224591772; 56604455300 | E16: Aspect sentiment triplet extraction based on data augmentation and task feedback | F16: 2024.0 | G16: Journal of Intelligent Information Systems | H16: 62 | I16: 6.0 | K16: 1659.0 | L16: 1683.0 | M16: 24.0 | N16: 1.0 | O16: 10.1007/s10844-024-00855-y | P16: https://www.scopus.com/inward/record.uri?eid=2-s2.0-85193611718&doi=10.1007%2fs10844-024-00855-y&partnerID=40&md5=d28e048555309a8c7d1b6f0ea37386d1 | Q16: School of Computer Science and Engineering, Central South University, Changsha, China; China Mobile Research Institute, Beijing, China | R16: Liu S., School of Computer Science and Engineering, Central South University, Changsha, China; Lu T., School of Computer Science and Engineering, Central South University, Changsha, China; Li K., School of Computer Science and Engineering, Central South University, Changsha, China; Liu W., China Mobile Research Institute, Beijing, China | S16: Aspect sentiment triplet extraction (ASTE), which focuses on mining the triplets (aspect, opinion, sentiment), is a complex and integrated subtask in aspect-based sentiment analysis. It is widely used in market research, product design and promotion, online comment analysis, and so on. Although significant progress has been achieved in existing methods, several challenges remain, such as data scarcity and the separation of span extraction and sentiment classification. Therefore, this paper adds data augmentation and task feedback based on the bidirectional machine reading comprehension model. Before training the model, the data augmentation module applies mask prediction and mark replacement to enrich the data. Span extraction and sentiment classification are two tasks during ASTE. We adopt the direct span extraction method with one classifier to avoid the error accumulation caused by multiple classifiers and to improve the adaptive ability between different datasets. In addition, we fuse the text features derived from the above two tasks for sentiment classification. Based on the feature fusion, the task feedback module is established to alleviate the task separation. Extensive experiments verify the effectiveness of our method. The code is available at https://github.com/zhenzhen313/BMRC-with-DA-and-TF. ¬© The Author(s), under exclusive licence to Springer Science+Business Media, LLC, part of Springer Nature 2024. | T16: Aspect sentiment triplet extraction; Bidirectional machine reading comprehension; Data augmentation; Feature fusion; Task feedback | U16: Classification (of information); Data mining; Market Research; Product design; Sentiment analysis; Aspect sentiment triplet extraction; Bidirectional machine reading comprehension; Data augmentation; Features fusions; Market researches; Reading comprehension; Sentiment analysis; Sentiment classification; Subtask; Task feedback; Extraction | Z16: Fundamental Research Funds for Central Universities of the Central South University; Central South University, CSU; Natural Science Foundation of Hunan Province, (2023JJ30700); Natural Science Foundation of Hunan Province | AA16: This work was supported in part by Hunan Provincial Natural Science Foundation of China under Grant 2023JJ30700, and in part by the Fundamental Research Funds for the Central Universities of Central South University. We are grateful for resources from the High Performance Computing Center of Central South University. | AB16: AlBadani B., Dong J., Shi R., Et al., Smgnn: span-to-span multi-channel graph neural network for aspect-sentiment triplet extraction, Journal of Intelligent Information Systems, 61, 3, pp. 695-715, (2023); Cahuantzi R., Chen X., Guttel S., A comparison of LSTM and GRU networks for learning symbolic sequences, Intelligent Computing, 739, pp. 771-785, (2023); Chen H., Zhai Z., Feng F., Et al., Enhanced multi-channel graph convolutional network for aspect sentiment triplet extraction, Proceedings of the 60Th Annual Meeting of the Association for Computational Linguistics, 1, pp. 2974-2985, (2022); Chen S., Wang Y., Liu J., Et al., Bidirectional machine reading comprehension for aspect sentiment triplet extraction, Proceedings of the AAAI Conference on Artificial Intelligence, 35, 14, pp. 12666-12674, (2021); Chen Y., Keming C., Sun X., Et al., A span-level bidirectional network for aspect sentiment triplet extraction, Proceedings of the 2022 Conference on Empirical Methods in Natural Language Processing, pp. 4300-4309, (2022); Chen Z., Qian T., Relation-aware collaborative learning for unified aspect-based sentiment analysis, Proceedings of the 58Th Annual Meeting of the Association for Computational Linguistics, pp. 3685-3694, (2020); Dave K., Lawrence S., Pennock D.M., Mining the peanut gallery: opinion extraction and semantic classification of product reviews, Proceedings of the 12th International Conference on World Wide Web, pp. 519-528, (2003); Devlin J., Chang M.W., Lee K., Et al., BERT: Pre-training of deep bidirectional transformers for language understanding, Proceedings of the 2019 Conference of the North American Chapter of the Association for Computational Linguistics: Human Language Technologies, Volume 1, Long and Short Papers, pp. 4171-4186, (2019); Di Caro L., Grella M., Sentiment analysis via dependency parsing, Computer Standards & Interfaces, 35, 5, pp. 442-453, (2013); Fei H., Ren Y., Zhang Y., Et al., Nonautoregressive encoder-decoder neural framework for end-to-end aspect-based sentiment triplet extraction, IEEE Transactions on Neural Networks and Learning Systems, 34, 9, pp. 5544-5556, (2023); Hu M., Liu B., Mining and summarizing customer reviews, Proceedings of the Tenth ACM SIGKDD International Conference on Knowledge Discovery and Data Mining, pp. 168-177, (2004); Karimi A., Rossi L., Prati A., AEDA: An easier data augmentation technique for text classification, pp. 2748-2754, (2021); Li X., Bing L., Li P., Et al., A unified model for opinion target extraction and target sentiment prediction, Proceedings of the AAAI Conference on Artificial Intelligence, 33, 1, pp. 6714-6721, (2019); Li Y., Cohn T., Baldwin T., Robust training under linguistic adversity, Proceedings of the 15th Conference of the European Chapter of the Association for Computational Linguistics: Volume 2, Short Papers, pp. 21-27, (2017); Liang B., Luo W., Li X., Et al., Enhancing aspect-based sentiment analysis with supervised contrastive learning, Proceedings of the 30th ACM International Conference on Information & Knowledge Management, pp. 3242-3247, (2021); Lin C., He Y., Joint sentiment/topic model for sentiment analysis, Proceedings of the 18th ACM Conference on Information and Knowledge Management, pp. 375-384, (2009); Liu S., Li K., Li Z., A robustly optimized BMRC for aspect sentiment triplet extraction, Proceedings of the 2022 Conference of the North American Chapter of the Association for Computational Linguistics: Human Language Technologies, pp. 272-278, (2022); Loshchilov I., Hutter F., Decoupled Weight Decay Regularization, (2017); Mao Y., Shen Y., Yu C., Et al., A joint training dual-MRC framework for aspect based sentiment analysis, Proceedings of the AAAI Conference on Artificial Intelligence, 35, 15, pp. 13543-13551, (2021); Peng H., Xu L., Bing L., Et al., Knowing what, how and why: A near complete solution for aspect-based sentiment analysis, Proceedings of the AAAI Conference on Artificial Intelligence, 34, 5, pp. 8600-8607, (2020); Pontiki M., Galanis D., Pavlopoulos J., Et al., SemEval-2014 task 4: Aspect based sentiment analysis, Proceedings of the 8th International Workshop on Semantic Evaluation (SemEval 2014), pp. 27-35, (2014); Pontiki M., Galanis D., Papageorgiou H., Et al., SemEval-2015 task 12: Aspect based sentiment analysis, Proceedings of the 9Th International Workshop on Semantic Evaluation (Semeval 2015), pp. 486-495, (2015); Pontiki M., Galanis D., Papageorgiou H., Et al., SemEval-2016 task 5: Aspect based sentiment analysis, Proceedings of the 10Th International Workshop on Semantic Evaluation, pp. 19-30, (2016); Ravi K., Ravi V., A survey on opinion mining and sentiment analysis: Tasks, approaches and applications, Knowledge-Based Systems, 89, pp. 14-46, (2015); Ren S., Zhang J., Li L., Et al., Text AutoAugment: Learning compositional augmentation policy for text classification, Proceedings of the 2021 Conference on Empirical Methods in Natural Language Processing, pp. 9029-9043, (2021); Singh L.G., Singh S.R., Empirical study of sentiment analysis tools and techniques on societal topics, Journal of Intelligent Information Systems, 56, 2, pp. 379-407, (2021); Sun L., Xia C., Yin W., Et al., Mixup-transformer: Dynamic data augmentation for NLP tasks, Proceedings of the 28th International Conference on Computational Linguistics, pp. 3436-3440, (2020); Toh Z., DLIREC: Aspect term extraction and term polarity classification system, Proceedings of the 8th International Workshop on Semantic Evaluation (SemEval 2014), pp. 235-240, (2014); Wang B., Ding L., Zhong Q., Et al., A contrastive cross-channel data augmentation framework for aspect-based sentiment analysis, Proceedings of the 29Th International Conference on Computational Linguistics, pp. 6691-6704, (2022); Wang Q., Wen Z., Zhao Q., Et al., Progressive self-training with discriminator for aspect term extraction, Proceedings of the 2021 Conference on Empirical Methods in Natural Language Processing, pp. 257-268, (2021); Wang Y., Chen Z., Chen S., Es-aste: enhanced span-level framework for aspect sentiment triplet extraction, Journal of Intelligent Information Systems, 60, 3, pp. 593-612, (2023); Wei J., Zou K., EDA: Easy data augmentation techniques for boosting performance on text classification tasks, Proceedings of the 2019 Conference on Empirical Methods in Natural Language Processing and the 9Th International Joint Conference on Natural Language Processing (EMNLP-IJCNLP), pp. 6382-6388, (2019); Wu Z., Ying C., Zhao F., Et al., Grid tagging scheme for aspect-oriented fine-grained opinion extraction, Findings of the Association for Computational Linguistics: EMNLP 2020, pp. 2576-2585, (2020); Xu L., Li H., Lu W., Et al., Position-aware tagging for aspect sentiment triplet extraction, Proceedings of the 2020 Conference on Empirical Methods in Natural Language Processing (EMNLP), pp. 2339-2349, (2020); Xu L., Chia Y.K., Bing L., Learning span-level interactions for aspect sentiment triplet extraction, Proceedings of the 59Th Annual Meeting of the Association for Computational Linguistics and the 11Th International Joint Conference on Natural Language Processing, 1, pp. 4755-4766, (2021); Yan H., Dai J., Ji T., Et al., A unified generative framework for aspect-based sentiment analysis, Proceedings of the 59Th Annual Meeting of the Association for Computational Linguistics and the 11Th International Joint Conference on Natural Language Processing, 1, pp. 2416-2429, (2021); Yu G., Liu L., Jiang H., Et al., Making better use of training corpus: Retrieval-based aspect sentiment triplet extraction via label interpolation, Findings of the Association for Computational Linguistics: ACL 2023, pp. 4914-4927, (2023); Zhang C., Li Q., Song D., Et al., A multi-task learning framework for opinion triplet extraction, Findings of the Association for Computational Linguistics: EMNLP 2020, pp. 819-828, (2020); Zhang L., Liu B., Aspect and entity extraction for opinion mining, pp. 1-40, (2014); Zhang W., Li X., Deng Y., Et al., Towards generative aspect-based sentiment analysis, Proceedings of the 59Th Annual Meeting of the Association for Computational Linguistics and the 11Th International Joint Conference on Natural Language Processing, 2, pp. 504-510, (2021); Zhang Y., Ding Q., Zhu Z., Et al., Enhancing aspect and opinion terms semantic relation for aspect sentiment triplet extraction, Journal of Intelligent Information Systems, 59, 2, pp. 523-542, (2022); Zhou S., Qian T., On the strength of sequence labeling and generative models for aspect sentiment triplet extraction, Findings of the Association for Computational Linguistics: ACL 2023, pp. 12038-12050, (2023); Zhu L., Zhu X., Guo J., Et al., Exploring rich structure information for aspect-based sentiment classification, Journal of Intelligent Information Systems, 60, 1, pp. 97-117, (2023) | AC16: W. Liu; China Mobile Research Institute, Beijing, China; email: liuweihuayjy@chinamobile.com | AE16: Springer | AK16: 9259902 | AM16: JIISE | AO16: English | AP16: J Intell Inform Syst | AQ16: Article | AR16: Final | AT16: Scopus | AU16: 2-s2.0-85193611718 | AV16: q17 | AW16: Scopus | AX16: ? | AY16: =IF(AX16=TRUE,1,IF(AX16=FALSE,0,-1)) -> -1 | AZ16: TRUE | BA16: =IF(AZ16=TRUE,1,IF(AZ16=FALSE,0,-1)) -> 1 | BB16: ? | BC16: =IF(BB16=TRUE,1,IF(BB16=FALSE,0,-1)) -> -1 | BD16: 1 | BE16: 1 | BF16: 1 | BG16: 1 | BH16: =IF(BG16=1,"Yes",IF(BG16=-1,"Doubt","No")) -> Yes | BI16: =IF(BF16=1,"Yes","No") -> Yes | BJ16: 1 | BK16: Aspect sentiment triplet extraction. (!)
A17: 59 | B17: Sazzed S. | C17: Sazzed, Salim (57201119659) | D17: 57201119659 | E17: BanglaBioMed: A Biomedical Named-Entity Annotated Corpus for Bangla (Bengali) | F17: 2022.0 | G17: Proceedings of the Annual Meeting of the Association for Computational Linguistics | K17: 323.0 | L17: 329.0 | M17: 6.0 | N17: 10.0 | O17: 10.18653/v1/2022.bionlp-1.31 | P17: https://www.scopus.com/inward/record.uri?eid=2-s2.0-85149127360&doi=10.18653%2fv1%2f2022.bionlp-1.31&partnerID=40&md5=d63cc0d3566456ba1830bb4220d941e6 | Q17: Old Dominion University, Norfolk, VA, United States | R17: Sazzed S., Old Dominion University, Norfolk, VA, United States | S17: Recognizing biomedical entities in the text has significance in biomedical and health science research, as it benefits myriad downstream tasks, including entity linking, relation extraction, or entity resolution. While English and a few other widely used languages enjoy ample resources for automatic biomedical entity recognition, it is not the case for Bangla, a low-resource language. On that account, in this paper, we introduce BanglaBioMed, a Bangla biomedical named entity (NE) annotated dataset in standard IOB format, the first of its kind, consisting of over 12000 tokens annotated with the biomedical entities. The corpus is created by collecting Bangla text from a list of health articles and then annotated with four distinct types of entities: Anatomy (AN), Chemical and Drugs (CD), Disease and Symptom (DS), and Medical Procedure (MP). We provide the details of the entire data collection and annotation procedure and illustrate various statistics of the created corpus. Our developed corpus is a much-needed addition to the Bangla NLP resource that will facilitate biomedical NLP research in Bangla. ¬© 2022 Association for Computational Linguistics. | U17: Character recognition; Computational linguistics; Bengalis; Biomedical science; Down-stream; Entity recognition; Entity resolutions; Health science; Low resource languages; Named entities; Relation extraction; Science research; Natural language processing systems | AB17: Bhowmick Anirban, Jana Abhik, Sentiment analysis for bengali using transformer based models; Bodini Matteo, Opinion mining from machine translated bangla reviews with stacked contractive auto-encoders, Journal of Ambient Intelligence and Humanized Computing, pp. 1-13, (2022); Carrino Casimiro Pio, Armengol-Estape Jordi, de Gibert Bonet Ona, Gutierrez-Fandino Asier, Gonzalez-Agirre Aitor, Krallinger Martin, Villegas Marta, Spanish biomedical crawled corpus: A large, diverse dataset for spanish biomedical language models, (2021); Dogan Rezarta Islamaj, Leaman Robert, Lu Zhiyong, Ncbi disease corpus: a resource for disease name recognition and concept normalization, Journal of biomedical informatics, 47, pp. 1-10, (2014); Abdullah Faruque M, Rahman Saifur, Chakraborty Partha, Choudhury Tanupriya, Um Jung-Sup, Singh Thipendra Pal, Ascertaining polarity of public opinions on bangladesh cricket using machine learning techniques, Spatial Information Research, pp. 1-8, (2021); Giorgi John M, Bader Gary D, Towards reliable named entity recognition in the biomedical domain, Bioinformatics, 36, 1, pp. 280-286, (2020); Gonzalez-Agirre Aitor, Marimon Montserrat, Intxaurrondo Ander, Rabal Obdulia, Villegas Marta, Krallinger Martin, Pharmaconer: Pharmacological substances, compounds and proteins named entity recognition track, Proceedings of The 5th Workshop on BioNLP Open Shared Tasks, pp. 1-10, (2019); Hastings Janna, Owen Gareth, Dekker Adriano, Ennis Marcus, Kale Namrata, Muthukrishnan Venkatesh, Turner Steve, Swainston Neil, Mendes Pedro, Steinbeck Christoph, Chebi in 2016: Improved services and an expanding collection of metabolites, Nucleic acids research, 44, D1, pp. D1214-D1219, (2016); Ishmam Alvi Md, Sharmin Sadia, Hateful speech detection in public facebook pages for the bengali language, 2019 18th IEEE International Conference On Machine Learning And Applications (ICMLA), pp. 555-560, (2019); Karim Md Rezaul, Dey Sumon Kanti, Islam Tanhim, Sarker Sagor, Menon Mehadi Hasan, Hossain Kabir, Hossain Md Azam, Decker Stefan, Deephateexplainer: Explainable hate speech detection in under-resourced bengali language, 2021 IEEE 8th International Conference on Data Science and Advanced Analytics (DSAA), pp. 1-10, (2021); Karimi Sarvnaz, Metke-Jimenez Alejandro, Kemp Madonna, Wang Chen, Cadec: A corpus of adverse drug event annotations, Journal of biomedical informatics, 55, pp. 73-81, (2015); Kim J-D, Ohta Tomoko, Tateisi Yuka, Tsujii Junichi, Genia corpusa semantically annotated corpus for bio-textmining, Bioinformatics, 19, pp. i180-i182, (2003); Kim Jin-Dong, Ohta Tomoko, 'ichi Tsujii Jun, Corpus annotation for mining biomedical events from literature, BMC bioinformatics, 9, 1, pp. 1-25, (2008); Kolarik Corinna, Klinger Roman, Friedrich Christoph M, Hofmann-Apitius Martin, Fluck Juliane, Chemical names: terminological resources and corpora annotation, Workshop on Building and evaluating resources for biomedical text mining (6th edition of the Language Resources and Evaluation Conference), (2008); Mitrofan Maria, Bootstrapping a romanian corpus for medical named entity recognition, RANLP, pp. 501-509, (2017); Mitrofan Maria, Tufis Dan, Bioro: The biomedical corpus for the romanian language, Proceedings of the Eleventh International Conference on Language Resources and Evaluation (LREC 2018), (2018); Mowery Danielle L, Velupillai Sumithra, Chapman Wendy, Medical diagnosis lost in translation-analysis of uncertainty and negation expressions in english and swedish clinical texts, BioNLP: Proceedings of the 2012 Workshop on Biomedical Natural Language Processing, pp. 56-64, (2012); Murphy Tara, McIntosh Tara, Cur-ran James R, Named entity recognition for astronomy literature, Proceedings of the Australasian Language Technology Workshop 2006, pp. 59-66, (2006); Neves Mariana, Damaschun Alexander, Kurtz Andreas, Leser Ulf, Annotating and evaluating text for stem cell research, Proceedings of the Third Workshop on Building and Evaluation Resources for Biomedical Text Mining (BioTxtM 2012) at Language Resources and Evaluation (LREC), pp. 16-23, (2012); Pyysalo Sampo, Ginter Filip, Heimonen Juho, Bjorne Jari, Boberg Jorma, Jarvinen Jouni, Salakoski Tapio, Bioinfer: a corpus for information extraction in the biomedical domain, BMC bioinformatics, 8, 1, pp. 1-24, (2007); Sang Erik F, De Meulder Fien, Introduction to the conll-2003 shared task: Language-independent named entity recognition, (2003); Sazzed Salim, Cross-lingual sentiment classification in low-resource bengali language, Proceedings of the sixth workshop on noisy user-generated text (W-NUT 2020), pp. 50-60, (2020); Sazzed Salim, Development of sentiment lexicon in bengali utilizing corpus and cross-lingual resources, 2020 IEEE 21st International conference on information reuse and integration for data science (IRI), pp. 237-244, (2020); Sazzed Salim, Abusive content detection in transliterated bengali-english social media corpus, Proceedings of the Fifth Workshop on Computational Approaches to Linguistic Code-Switching, pp. 125-130, (2021); Sazzed Salim, Identifying vulgarity in bengali social media textual content, PeerJ Computer Science, 7, (2021); Sazzed Salim, Jayarathna Sampath, A sentiment classification in bengali and machine translated english corpus, 2019 IEEE 20th international conference on information reuse and integration for data science (IRI), pp. 107-114, (2019); Scepanovic Sanja, Martin-Lopez Enrique, Quercia Daniele, Baykaner Khan, Extracting medical entities from social media, Proceedings of the ACM Conference on Health, Inference, and Learning, pp. 170-181, (2020); Stojanov Riste, Popovski Gorjan, Cenikj Gjorgjina, Seljak Barbara Korousic, Eftimov Tome, Et al., A fine-tuned bidirectional encoder representations from transformers model for food named-entity recognition: Algorithm development and validation, Journal of Medical Internet Research, 23, 8, (2021); Sun Cong, Yang Zhihao, Transfer learning in biomedical named entity recognition: an evaluation of bert in the pharmaconer task, Proceedings of The 5th Workshop on BioNLP Open Shared Tasks, pp. 100-104, (2019); Tanabe Lorraine, Xie Natalie, Thom Lynne H, Matten Wayne, John Wilbur W, Gene-tag: a tagged corpus for gene/protein named entity recognition, BMC bioinformatics, 6, 1, pp. 1-7, (2005); Tjong Erik F., Sang Kim, Veenstra Jorn, Representing text chunks, Ninth Conference of the European Chapter of the Association for Computational Linguistics, pp. 173-179, (1999); Velupillai Sumithra, Shades of certainty: annotation and classification of swedish medical records, (2012); Zweigenbaum Pierre, Baud Robert, Bur-gun Anita, Namer Fiammetta, Jarrousse Eric, Grabar Natalia, Ruch Patrick, Duff Franck Le, Forget Jean-Francois, Douyere Magaly, Et al., Umlf: a unified medical lexicon for french, International Journal of Medical Informatics, 74, 2-4, pp. 119-124, (2005) | AC17: S. Sazzed; Old Dominion University, Norfolk, United States; email: ssazz001@odu.edu | AE17: Association for Computational Linguistics (ACL) | AG17: 21st Workshop on Biomedical Language Processing, BioNLP 2022 at the Association for Computational Linguistics Conference, ACL 2022 | AH17: 44707 | AI17: Dublin | AJ17: 182391.0 | AK17: 0736587X | AL17: 978-195591727-8 | AO17: English | AP17: Proc. Annu. Meet. Assoc. Comput Linguist. | AQ17: Conference paper | AR17: Final | AS17: All Open Access; Hybrid Gold Open Access | AT17: Scopus | AU17: 2-s2.0-85149127360 | AV17: q1 | AW17: Scopus | AX17: TRUE | AY17: =IF(AX17=TRUE,1,IF(AX17=FALSE,0,-1)) -> 1 | AZ17: TRUE | BA17: =IF(AZ17=TRUE,1,IF(AZ17=FALSE,0,-1)) -> 1 | BB17: TRUE | BC17: =IF(BB17=TRUE,1,IF(BB17=FALSE,0,-1)) -> 1 | BD17: 1 | BE17: 0 | BF17: 0 | BG17: 0 | BH17: =IF(BG17=1,"Yes",IF(BG17=-1,"Doubt","No")) -> No | BI17: =IF(BF17=1,"Yes","No") -> No | BJ17: 0 | BK17: Only focus on extracting entities. It is centered on biomedical domain.
